[
  {
    "User": "Andreas",
    "Artists": [
      "Stellar Revival"
    ],
    "ArtistsString": "Stellar Revival",
    "Track": "The Crazy Ones",
    "TrackId": "0TSyISpqnV0Q3wsYtnJFyl",
    "Genres": [
      "hard alternative",
      "heavy alternative"
    ],
    "GenresString": "hard alternative; heavy alternative"
  },
  {
    "User": "Andreas",
    "Artists": [
      "Billy Talent"
    ],
    "ArtistsString": "Billy Talent",
    "Track": "Rusted From The Rain",
    "TrackId": "1VbsSYNXKBpjPvqddk8zjs",
    "Genres": [
      "alternative metal",
      "modern rock",
      "nu metal",
      "pop punk",
      "post-grunge",
      "punk"
    ],
    "GenresString": "alternative metal; modern rock; nu metal; pop punk; post-grunge; punk"
  },
  {
    "User": "Andreas",
    "Artists": [
      "Turbonegro"
    ],
    "ArtistsString": "Turbonegro",
    "Track": "All My Friends Are Dead",
    "TrackId": "6fEztciYVlIyWTBe66clVj",
    "Genres": [
      "garage rock",
      "norwegian rock",
      "punk",
      "skate punk",
      "stoner rock",
      "swedish indie rock"
    ],
    "GenresString": "garage rock; norwegian rock; punk; skate punk; stoner rock; swedish indie rock"
  },
  {
    "User": "Andreas",
    "Artists": [
      "Red"
    ],
    "ArtistsString": "Red",
    "Track": "Breathe Into Me",
    "TrackId": "0DLjcGTmH2NV9AjzecAGT6",
    "Genres": [
      "alternative metal",
      "christian alternative rock",
      "christian rock",
      "nu metal",
      "post-grunge",
      "rap metal",
      "rap rock"
    ],
    "GenresString": "alternative metal; christian alternative rock; christian rock; nu metal; post-grunge; rap metal; rap rock"
  },
  {
    "User": "Andreas",
    "Artists": [
      "Emigrate"
    ],
    "ArtistsString": "Emigrate",
    "Track": "My World",
    "TrackId": "3GwzYHGrRn7wMfRtvbjg2U",
    "Genres": [
      "alternative metal",
      "industrial",
      "industrial metal",
      "industrial rock",
      "neue deutsche harte",
      "nu metal"
    ],
    "GenresString": "alternative metal; industrial; industrial metal; industrial rock; neue deutsche harte; nu metal"
  },
  {
    "User": "Andreas",
    "Artists": [
      "Eighteen Visions"
    ],
    "ArtistsString": "Eighteen Visions",
    "Track": "Victim",
    "TrackId": "38RTTDR84odCz5gQrLuZQR",
    "Genres": [
      "christian hardcore",
      "mathcore",
      "melodic metalcore",
      "metalcore",
      "post-hardcore",
      "screamo"
    ],
    "GenresString": "christian hardcore; mathcore; melodic metalcore; metalcore; post-hardcore; screamo"
  },
  {
    "User": "Andreas",
    "Artists": [
      "Dead By Sunrise"
    ],
    "ArtistsString": "Dead By Sunrise",
    "Track": "Inside Of Me",
    "TrackId": "7GGJ7uPEFfjhfx2UD3ZNYX",
    "Genres": [
      "alternative metal",
      "nu metal",
      "post-grunge",
      "rap metal",
      "rap rock"
    ],
    "GenresString": "alternative metal; nu metal; post-grunge; rap metal; rap rock"
  },
  {
    "User": "Andreas",
    "Artists": [
      "Girl On Fire"
    ],
    "ArtistsString": "Girl On Fire",
    "Track": "The Takedown",
    "TrackId": "1X8ahBi1Y4j5hTFbFdw25s",
    "Genres": [
      "hard alternative",
      "post-screamo"
    ],
    "GenresString": "hard alternative; post-screamo"
  },
  {
    "User": "Andreas",
    "Artists": [
      "Amon Amarth"
    ],
    "ArtistsString": "Amon Amarth",
    "Track": "Twilight Of The Thunder God",
    "TrackId": "5u3l2TONYacJgmRPQVaF9y",
    "Genres": [
      "alternative metal",
      "groove metal",
      "melodic death metal",
      "melodic metalcore",
      "metal",
      "nu metal",
      "power metal",
      "progressive metal",
      "swedish metal",
      "viking metal"
    ],
    "GenresString": "alternative metal; groove metal; melodic death metal; melodic metalcore; metal; nu metal; power metal; progressive metal; swedish metal; viking metal"
  },
  {
    "User": "Andreas",
    "Artists": [
      "Primer 55"
    ],
    "ArtistsString": "Primer 55",
    "Track": "Loose",
    "TrackId": "77RhRdYVOO1PJNcNwourTo",
    "Genres": [
      "alternative metal",
      "groove metal",
      "industrial metal",
      "nu metal",
      "rap metal",
      "rap rock"
    ],
    "GenresString": "alternative metal; groove metal; industrial metal; nu metal; rap metal; rap rock"
  },
  {
    "User": "Andreas",
    "Artists": [
      "Atreyu"
    ],
    "ArtistsString": "Atreyu",
    "Track": "Blow",
    "TrackId": "1QQPdR1BYLoZyYe8C8XW9C",
    "Genres": [
      "alternative metal",
      "emo",
      "groove metal",
      "melodic metalcore",
      "metalcore",
      "nu metal",
      "pop punk",
      "post-grunge",
      "rap metal",
      "rap rock",
      "screamo"
    ],
    "GenresString": "alternative metal; emo; groove metal; melodic metalcore; metalcore; nu metal; pop punk; post-grunge; rap metal; rap rock; screamo"
  },
  {
    "User": "Andreas",
    "Artists": [
      "Sick Puppies"
    ],
    "ArtistsString": "Sick Puppies",
    "Track": "Gunfight",
    "TrackId": "0R5tVWACu5evNC8bwHFeY0",
    "Genres": [
      "alternative metal",
      "nu metal",
      "pop punk",
      "post-grunge",
      "rap metal",
      "rap rock"
    ],
    "GenresString": "alternative metal; nu metal; pop punk; post-grunge; rap metal; rap rock"
  },
  {
    "User": "Andreas",
    "Artists": [
      "Eluveitie"
    ],
    "ArtistsString": "Eluveitie",
    "Track": "Inis Mona",
    "TrackId": "1OoFeSJP5g9IrC3xFjoS1a",
    "Genres": [
      "bow pop",
      "celtic rock",
      "folk metal",
      "melodic death metal",
      "metal",
      "power metal",
      "viking metal"
    ],
    "GenresString": "bow pop; celtic rock; folk metal; melodic death metal; metal; power metal; viking metal"
  },
  {
    "User": "Andreas",
    "Artists": [
      "Sixx:A.M."
    ],
    "ArtistsString": "Sixx:A.M.",
    "Track": "This Is Gonna Hurt",
    "TrackId": "4VYHaLVaCspuhjHEmfXtL3",
    "Genres": [
      "alternative metal",
      "glam metal",
      "heavy christmas",
      "nu metal",
      "post-grunge",
      "rap metal",
      "rap rock"
    ],
    "GenresString": "alternative metal; glam metal; heavy christmas; nu metal; post-grunge; rap metal; rap rock"
  },
  {
    "User": "Andreas",
    "Artists": [
      "Equilibrium"
    ],
    "ArtistsString": "Equilibrium",
    "Track": "Blut im Auge",
    "TrackId": "0qkAeodGJPi05A3W73F03v",
    "Genres": [
      "folk metal",
      "german metal",
      "melodic death metal",
      "metal",
      "neue deutsche harte",
      "power metal",
      "progressive metal",
      "symphonic metal",
      "viking metal"
    ],
    "GenresString": "folk metal; german metal; melodic death metal; metal; neue deutsche harte; power metal; progressive metal; symphonic metal; viking metal"
  },
  {
    "User": "Andreas",
    "Artists": [
      "Nickelback"
    ],
    "ArtistsString": "Nickelback",
    "Track": "Burn it to the Ground",
    "TrackId": "4pckuF6VOu58o1pMFUdlPW",
    "Genres": [
      "alternative metal",
      "canadian pop",
      "nu metal",
      "post-grunge"
    ],
    "GenresString": "alternative metal; canadian pop; nu metal; post-grunge"
  },
  {
    "User": "Andreas",
    "Artists": [
      "Dirty Wormz"
    ],
    "ArtistsString": "Dirty Wormz",
    "Track": "God of Waar",
    "TrackId": "4kC6OPUkP1tDfGBSaiVKIy",
    "Genres": [
      "rap metal",
      "rap metalcore",
      "rap rock"
    ],
    "GenresString": "rap metal; rap metalcore; rap rock"
  },
  {
    "User": "Andreas",
    "Artists": [
      "Mikey Ruckus",
      "Zardonic"
    ],
    "ArtistsString": "Mikey Ruckus; Zardonic",
    "Track": "Bring It On (feat. Mikey Rukus)",
    "TrackId": "6s5aDWfExJnYYD09sLGryb",
    "Genres": [
      "darkstep",
      "neurofunk"
    ],
    "GenresString": "darkstep; neurofunk"
  },
  {
    "User": "Andreas",
    "Artists": [
      "The Wreckage"
    ],
    "ArtistsString": "The Wreckage",
    "Track": "Breaking Through",
    "TrackId": "781bCQjAUwwvfqlLV1ktnH",
    "Genres": [],
    "GenresString": ""
  },
  {
    "User": "Andreas",
    "Artists": [
      "Anti-Flag"
    ],
    "ArtistsString": "Anti-Flag",
    "Track": "This Is the End (For You My Friend)",
    "TrackId": "1jvqZQtbBGK5GJCGT615ao",
    "Genres": [
      "melodic hardcore",
      "pop punk",
      "punk",
      "ska punk",
      "skate punk"
    ],
    "GenresString": "melodic hardcore; pop punk; punk; ska punk; skate punk"
  },
  {
    "User": "Andreas",
    "Artists": [
      "Die Happy"
    ],
    "ArtistsString": "Die Happy",
    "Track": "Supersonic Speed",
    "TrackId": "5xpzdbPQptivIlK3TUpQXy",
    "Genres": [
      "german pop"
    ],
    "GenresString": "german pop"
  },
  {
    "User": "Andreas",
    "Artists": [
      "Russkaja"
    ],
    "ArtistsString": "Russkaja",
    "Track": "Energia",
    "TrackId": "55wnDa7AiAuZeWZfUK5eIZ",
    "Genres": [
      "russian punk"
    ],
    "GenresString": "russian punk"
  },
  {
    "User": "Andreas",
    "Artists": [
      "Dream Evil"
    ],
    "ArtistsString": "Dream Evil",
    "Track": "The Chosen Ones",
    "TrackId": "7FQvFYg88JndjHvd5tBxwI",
    "Genres": [
      "hard rock",
      "melodic death metal",
      "metal",
      "neo classical metal",
      "power metal",
      "progressive metal",
      "speed metal",
      "viking metal"
    ],
    "GenresString": "hard rock; melodic death metal; metal; neo classical metal; power metal; progressive metal; speed metal; viking metal"
  },
  {
    "User": "Andreas",
    "Artists": [
      "zebrahead"
    ],
    "ArtistsString": "zebrahead",
    "Track": "Falling Apart",
    "TrackId": "5w4QQY7P68z4Q2t441gF2V",
    "Genres": [
      "alternative metal",
      "emo",
      "funk metal",
      "modern rock",
      "nu metal",
      "pop punk",
      "post-grunge",
      "punk",
      "rap metal",
      "rap rock",
      "skate punk"
    ],
    "GenresString": "alternative metal; emo; funk metal; modern rock; nu metal; pop punk; post-grunge; punk; rap metal; rap rock; skate punk"
  },
  {
    "User": "Andreas",
    "Artists": [
      "Anarchy Club"
    ],
    "ArtistsString": "Anarchy Club",
    "Track": "Behind The Mask",
    "TrackId": "60gcB78vhK5174cyKMkEuH",
    "Genres": [],
    "GenresString": ""
  },
  {
    "User": "Andreas",
    "Artists": [
      "Raised Fist"
    ],
    "ArtistsString": "Raised Fist",
    "Track": "Friends & Traitors",
    "TrackId": "0o700FqVYCvzdCYXxfX92m",
    "Genres": [
      "skate punk",
      "swedish alternative rock"
    ],
    "GenresString": "skate punk; swedish alternative rock"
  },
  {
    "User": "Andreas",
    "Artists": [
      "Clawfinger"
    ],
    "ArtistsString": "Clawfinger",
    "Track": "Biggest & The Best - Remastered version",
    "TrackId": "4KdCtL3tO5osDoxtZR1aqg",
    "Genres": [
      "alternative metal",
      "funk metal",
      "groove metal",
      "industrial metal",
      "neue deutsche harte",
      "nu metal",
      "rap metal",
      "rap rock"
    ],
    "GenresString": "alternative metal; funk metal; groove metal; industrial metal; neue deutsche harte; nu metal; rap metal; rap rock"
  },
  {
    "User": "Andreas",
    "Artists": [
      "Wolfmother"
    ],
    "ArtistsString": "Wolfmother",
    "Track": "Joker And The Thief",
    "TrackId": "6dNJ3lasVLPd0078T9yqlm",
    "Genres": [
      "alternative rock",
      "classic rock",
      "funk rock",
      "garage rock",
      "indie rock",
      "modern rock",
      "neo-psychedelic",
      "post-grunge",
      "rock"
    ],
    "GenresString": "alternative rock; classic rock; funk rock; garage rock; indie rock; modern rock; neo-psychedelic; post-grunge; rock"
  },
  {
    "User": "Andreas",
    "Artists": [
      "Heaven Shall Burn"
    ],
    "ArtistsString": "Heaven Shall Burn",
    "Track": "Black Tears",
    "TrackId": "3OZdcvibLrA7Jr9xw5W88D",
    "Genres": [
      "death core",
      "groove metal",
      "melodic death metal",
      "melodic metalcore",
      "metalcore",
      "neue deutsche harte",
      "nu metal"
    ],
    "GenresString": "death core; groove metal; melodic death metal; melodic metalcore; metalcore; neue deutsche harte; nu metal"
  },
  {
    "User": "Andreas",
    "Artists": [
      "Solence"
    ],
    "ArtistsString": "Solence",
    "Track": "Warriors",
    "TrackId": "6gsM7xmG68XjOuXtUjS4Rg",
    "Genres": [
      "post-screamo"
    ],
    "GenresString": "post-screamo"
  },
  {
    "User": "Björn",
    "Artists": [
      "Immolation"
    ],
    "ArtistsString": "Immolation",
    "Track": "When the Jackals Come",
    "TrackId": "3BW0bVxz8wD9vGfXvwrlEB",
    "Genres": [
      "black metal",
      "black thrash",
      "brutal death metal",
      "death metal",
      "deathgrind",
      "doom metal",
      "goregrind",
      "grindcore",
      "groove metal",
      "jazz metal",
      "metal",
      "pagan black metal",
      "post-doom metal",
      "speed metal",
      "symphonic black metal",
      "technical death metal",
      "thrash metal",
      "voidgaze"
    ],
    "GenresString": "black metal; black thrash; brutal death metal; death metal; deathgrind; doom metal; goregrind; grindcore; groove metal; jazz metal; metal; pagan black metal; post-doom metal; speed metal; symphonic black metal; technical death metal; thrash metal; voidgaze"
  },
  {
    "User": "Björn",
    "Artists": [
      "Winterfylleth"
    ],
    "ArtistsString": "Winterfylleth",
    "Track": "The Swart Raven",
    "TrackId": "2yUZbU9VIGQGoN0qVi4I33",
    "Genres": [
      "atmospheric black metal",
      "avantgarde metal",
      "black metal",
      "folk metal",
      "pagan black metal",
      "post-metal",
      "symphonic black metal",
      "viking metal",
      "voidgaze"
    ],
    "GenresString": "atmospheric black metal; avantgarde metal; black metal; folk metal; pagan black metal; post-metal; symphonic black metal; viking metal; voidgaze"
  },
  {
    "User": "Björn",
    "Artists": [
      "Autopsy"
    ],
    "ArtistsString": "Autopsy",
    "Track": "Puncturing the Grotesque",
    "TrackId": "7vbUe8nDcffNgQDA8OyyCi",
    "Genres": [
      "black death",
      "black metal",
      "black thrash",
      "brutal death metal",
      "crossover thrash",
      "crust punk",
      "death metal",
      "deathgrind",
      "doom metal",
      "goregrind",
      "grindcore",
      "groove metal",
      "metal",
      "speed metal",
      "technical death metal",
      "thrash metal"
    ],
    "GenresString": "black death; black metal; black thrash; brutal death metal; crossover thrash; crust punk; death metal; deathgrind; doom metal; goregrind; grindcore; groove metal; metal; speed metal; technical death metal; thrash metal"
  },
  {
    "User": "Björn",
    "Artists": [
      "Hanging Garden"
    ],
    "ArtistsString": "Hanging Garden",
    "Track": "Elysium",
    "TrackId": "23XDuqUXXS2jtnfdH3ZGDx",
    "Genres": [
      "doom metal",
      "funeral doom"
    ],
    "GenresString": "doom metal; funeral doom"
  },
  {
    "User": "Björn",
    "Artists": [
      "Eluveitie"
    ],
    "ArtistsString": "Eluveitie",
    "Track": "Rebirth",
    "TrackId": "2Q0nRqCBJRhAuiT7mXFFsW",
    "Genres": [
      "bow pop",
      "celtic rock",
      "folk metal",
      "melodic death metal",
      "metal",
      "power metal",
      "viking metal"
    ],
    "GenresString": "bow pop; celtic rock; folk metal; melodic death metal; metal; power metal; viking metal"
  },
  {
    "User": "Björn",
    "Artists": [
      "The Fright"
    ],
    "ArtistsString": "The Fright",
    "Track": "Oblivion",
    "TrackId": "3Cnhhc5JbdnqmI3P3fF4BQ",
    "Genres": [
      "horror punk"
    ],
    "GenresString": "horror punk"
  },
  {
    "User": "Björn",
    "Artists": [
      "F.K.Ü."
    ],
    "ArtistsString": "F.K.Ü.",
    "Track": "Friday the 13th Part 2",
    "TrackId": "41ihU3MPMbr0aeR1rgw2qk",
    "Genres": [
      "crossover thrash"
    ],
    "GenresString": "crossover thrash"
  },
  {
    "User": "Björn",
    "Artists": [
      "Wolfheart"
    ],
    "ArtistsString": "Wolfheart",
    "Track": "Shores Of The Lake Simpele",
    "TrackId": "4l3f3QMLfUN2LiI3gW3E6z",
    "Genres": [
      "folk metal",
      "gothic metal",
      "melodic death metal",
      "viking metal"
    ],
    "GenresString": "folk metal; gothic metal; melodic death metal; viking metal"
  },
  {
    "User": "Björn",
    "Artists": [
      "Death"
    ],
    "ArtistsString": "Death",
    "Track": "Painkiller",
    "TrackId": "4uOSpJxcpzeNCWXYoXGJM1",
    "Genres": [
      "alternative metal",
      "crossover thrash",
      "death metal",
      "deathgrind",
      "funk rock",
      "groove metal",
      "hard rock",
      "melodic death metal",
      "melodic metalcore",
      "metal",
      "nu metal",
      "power metal",
      "progressive metal",
      "speed metal",
      "technical death metal",
      "thrash metal"
    ],
    "GenresString": "alternative metal; crossover thrash; death metal; deathgrind; funk rock; groove metal; hard rock; melodic death metal; melodic metalcore; metal; nu metal; power metal; progressive metal; speed metal; technical death metal; thrash metal"
  },
  {
    "User": "Björn",
    "Artists": [
      "Wintersun"
    ],
    "ArtistsString": "Wintersun",
    "Track": "Beautiful Death - Live at Tuska Festival 2013",
    "TrackId": "364MWsvzAHXjVsuhChMgng",
    "Genres": [
      "finnish metal",
      "folk metal",
      "gothic metal",
      "melodic death metal",
      "metal",
      "neo classical metal",
      "power metal",
      "progressive metal",
      "symphonic black metal",
      "viking metal"
    ],
    "GenresString": "finnish metal; folk metal; gothic metal; melodic death metal; metal; neo classical metal; power metal; progressive metal; symphonic black metal; viking metal"
  },
  {
    "User": "Björn",
    "Artists": [
      "Vredehammer"
    ],
    "ArtistsString": "Vredehammer",
    "Track": "Suffocate All Light",
    "TrackId": "4tsbKHKXNOncUoyNxyVtQW",
    "Genres": [
      "cryptic black metal"
    ],
    "GenresString": "cryptic black metal"
  },
  {
    "User": "Björn",
    "Artists": [
      "Shining"
    ],
    "ArtistsString": "Shining",
    "Track": "Gyllene portarnas bro",
    "TrackId": "16ZgMsSzg3LfQF1SGpKoTA",
    "Genres": [
      "atmospheric black metal",
      "avantgarde metal",
      "black metal",
      "depressive black metal",
      "pagan black metal",
      "symphonic black metal",
      "viking metal",
      "voidgaze"
    ],
    "GenresString": "atmospheric black metal; avantgarde metal; black metal; depressive black metal; pagan black metal; symphonic black metal; viking metal; voidgaze"
  },
  {
    "User": "Björn",
    "Artists": [
      "Elvenking"
    ],
    "ArtistsString": "Elvenking",
    "Track": "Invoking the Woodland Spirit",
    "TrackId": "7iNRoYWYiRlZIIamw1f1bU",
    "Genres": [
      "folk metal",
      "gothic symphonic metal",
      "heavy christmas",
      "italian metal",
      "melodic death metal",
      "neo classical metal",
      "power metal",
      "progressive metal",
      "speed metal",
      "symphonic metal",
      "viking metal"
    ],
    "GenresString": "folk metal; gothic symphonic metal; heavy christmas; italian metal; melodic death metal; neo classical metal; power metal; progressive metal; speed metal; symphonic metal; viking metal"
  },
  {
    "User": "Björn",
    "Artists": [
      "Destruction"
    ],
    "ArtistsString": "Destruction",
    "Track": "United by Hatred",
    "TrackId": "4ulTQSXrli15DAjSkjGr4v",
    "Genres": [
      "black thrash",
      "crossover thrash",
      "death metal",
      "german metal",
      "groove metal",
      "hard rock",
      "latin metal",
      "metal",
      "nwobhm",
      "power metal",
      "speed metal",
      "thrash metal"
    ],
    "GenresString": "black thrash; crossover thrash; death metal; german metal; groove metal; hard rock; latin metal; metal; nwobhm; power metal; speed metal; thrash metal"
  },
  {
    "User": "Björn",
    "Artists": [
      "Debauchery"
    ],
    "ArtistsString": "Debauchery",
    "Track": "Blood for the Blood God",
    "TrackId": "52uzGBOafun0rfesVo2VLs",
    "Genres": [
      "brutal death metal",
      "death metal",
      "deathgrind",
      "german metal",
      "goregrind",
      "heavy christmas"
    ],
    "GenresString": "brutal death metal; death metal; deathgrind; german metal; goregrind; heavy christmas"
  },
  {
    "User": "Björn",
    "Artists": [
      "Throwdown"
    ],
    "ArtistsString": "Throwdown",
    "Track": "Holy Roller",
    "TrackId": "4cxStibJfYu9U66QbE7Yrw",
    "Genres": [
      "alternative metal",
      "christian hardcore",
      "groove metal",
      "hardcore",
      "melodic metalcore",
      "metalcore",
      "nu metal",
      "rap metal",
      "rap rock",
      "straight edge"
    ],
    "GenresString": "alternative metal; christian hardcore; groove metal; hardcore; melodic metalcore; metalcore; nu metal; rap metal; rap rock; straight edge"
  },
  {
    "User": "Björn",
    "Artists": [
      "Watain"
    ],
    "ArtistsString": "Watain",
    "Track": "Nuclear Alchemy",
    "TrackId": "2DDuylH5qi1JcSLt1Rxw5z",
    "Genres": [
      "atmospheric black metal",
      "avantgarde metal",
      "black metal",
      "black thrash",
      "dark black metal",
      "death metal",
      "metal",
      "pagan black metal",
      "swedish metal",
      "symphonic black metal",
      "viking metal",
      "voidgaze"
    ],
    "GenresString": "atmospheric black metal; avantgarde metal; black metal; black thrash; dark black metal; death metal; metal; pagan black metal; swedish metal; symphonic black metal; viking metal; voidgaze"
  },
  {
    "User": "Björn",
    "Artists": [
      "Honningbarna"
    ],
    "ArtistsString": "Honningbarna",
    "Track": "Noen Å Hate",
    "TrackId": "2HW5X6taMxv8WzrhdfyTiv",
    "Genres": [
      "norwegian hip hop",
      "norwegian indie",
      "norwegian pop",
      "norwegian rock"
    ],
    "GenresString": "norwegian hip hop; norwegian indie; norwegian pop; norwegian rock"
  },
  {
    "User": "Björn",
    "Artists": [
      "Powerflo"
    ],
    "ArtistsString": "Powerflo",
    "Track": "My M.O.",
    "TrackId": "49JXuJrpnVs8YrKF0W3rkP",
    "Genres": [
      "rap metal",
      "rap rock"
    ],
    "GenresString": "rap metal; rap rock"
  },
  {
    "User": "Björn",
    "Artists": [
      "Ringworm"
    ],
    "ArtistsString": "Ringworm",
    "Track": "Dawn of Decay",
    "TrackId": "6TnGaINykO7Pwv6NJv3irr",
    "Genres": [
      "chaotic hardcore",
      "crossover thrash",
      "hardcore",
      "mathcore",
      "metalcore",
      "rap metal",
      "straight edge"
    ],
    "GenresString": "chaotic hardcore; crossover thrash; hardcore; mathcore; metalcore; rap metal; straight edge"
  },
  {
    "User": "Björn",
    "Artists": [
      "Nekrokraft"
    ],
    "ArtistsString": "Nekrokraft",
    "Track": "Wrath of the Heavens",
    "TrackId": "35nrAw1mlZmV2LWNnqg0b7",
    "Genres": [],
    "GenresString": ""
  },
  {
    "User": "Björn",
    "Artists": [
      "Spectral Voice"
    ],
    "ArtistsString": "Spectral Voice",
    "Track": "Thresholds Beyond",
    "TrackId": "4zF71ri9gLObTWDbTf1vg6",
    "Genres": [],
    "GenresString": ""
  },
  {
    "User": "Björn",
    "Artists": [
      "Nightrage"
    ],
    "ArtistsString": "Nightrage",
    "Track": "In Abhorrence",
    "TrackId": "3Inqs6Rgmp8eHJBYAI9A8m",
    "Genres": [
      "melodic death metal",
      "melodic metalcore",
      "metalcore"
    ],
    "GenresString": "melodic death metal; melodic metalcore; metalcore"
  },
  {
    "User": "Björn",
    "Artists": [
      "Solution .45"
    ],
    "ArtistsString": "Solution .45",
    "Track": "Built on Sand",
    "TrackId": "3j8hEt5F9uy4yhZ5ANon1H",
    "Genres": [
      "melodic death metal",
      "melodic metalcore",
      "swedish metal"
    ],
    "GenresString": "melodic death metal; melodic metalcore; swedish metal"
  },
  {
    "User": "Björn",
    "Artists": [
      "The Kristet Utseende"
    ],
    "ArtistsString": "The Kristet Utseende",
    "Track": "Arunachala",
    "TrackId": "5cNaiCjCTapRIWfm4qEBtJ",
    "Genres": [
      "classic swedish pop",
      "danspunk",
      "swedish alternative rock",
      "swedish hip hop",
      "swedish punk"
    ],
    "GenresString": "classic swedish pop; danspunk; swedish alternative rock; swedish hip hop; swedish punk"
  },
  {
    "User": "Björn",
    "Artists": [
      "Eye of the Enemy"
    ],
    "ArtistsString": "Eye of the Enemy",
    "Track": "The Oath",
    "TrackId": "1ahAyhDcTN9Zt1BEwqdCB7",
    "Genres": [
      "melodic death metal"
    ],
    "GenresString": "melodic death metal"
  },
  {
    "User": "Björn",
    "Artists": [
      "Evil Invaders"
    ],
    "ArtistsString": "Evil Invaders",
    "Track": "As Life Slowly Fades",
    "TrackId": "0SAEZvNqChGaBcTjkMK9HP",
    "Genres": [
      "nwobhm",
      "nwothm",
      "speed metal"
    ],
    "GenresString": "nwobhm; nwothm; speed metal"
  },
  {
    "User": "Björn",
    "Artists": [
      "RAM"
    ],
    "ArtistsString": "RAM",
    "Track": "On Wings of No Return",
    "TrackId": "40zQYkGJAmISsnIKnd89Ih",
    "Genres": [
      "nwothm"
    ],
    "GenresString": "nwothm"
  },
  {
    "User": "Björn",
    "Artists": [
      "Cyhra"
    ],
    "ArtistsString": "Cyhra",
    "Track": "Karma",
    "TrackId": "7xNy4SaYMiPTJroKwnYQwG",
    "Genres": [],
    "GenresString": ""
  },
  {
    "User": "Björn",
    "Artists": [
      "Abominable Putridity"
    ],
    "ArtistsString": "Abominable Putridity",
    "Track": "Remnants of the Tortured",
    "TrackId": "0JtDVmlENJKk7l3xZJX6sW",
    "Genres": [
      "brutal death metal",
      "deathgrind",
      "goregrind",
      "progressive deathcore",
      "slam death metal",
      "technical death metal"
    ],
    "GenresString": "brutal death metal; deathgrind; goregrind; progressive deathcore; slam death metal; technical death metal"
  },
  {
    "User": "Eike",
    "Artists": [
      "Primer 55"
    ],
    "ArtistsString": "Primer 55",
    "Track": "Loose",
    "TrackId": "77RhRdYVOO1PJNcNwourTo",
    "Genres": [
      "alternative metal",
      "groove metal",
      "industrial metal",
      "nu metal",
      "rap metal",
      "rap rock"
    ],
    "GenresString": "alternative metal; groove metal; industrial metal; nu metal; rap metal; rap rock"
  },
  {
    "User": "Eike",
    "Artists": [
      "Jimmy Eat World"
    ],
    "ArtistsString": "Jimmy Eat World",
    "Track": "Bleed American",
    "TrackId": "4yAEzjMpN9RZxZLqjqmW0X",
    "Genres": [
      "alternative metal",
      "alternative rock",
      "emo",
      "modern rock",
      "neo mellow",
      "pop christmas",
      "pop punk",
      "pop rock",
      "post-grunge",
      "punk christmas"
    ],
    "GenresString": "alternative metal; alternative rock; emo; modern rock; neo mellow; pop christmas; pop punk; pop rock; post-grunge; punk christmas"
  },
  {
    "User": "Eike",
    "Artists": [
      "Long Distance Calling"
    ],
    "ArtistsString": "Long Distance Calling",
    "Track": "Black Paper Planes",
    "TrackId": "6ZvmAXqrALWGr0sytv66NO",
    "Genres": [
      "post rock",
      "post-metal"
    ],
    "GenresString": "post rock; post-metal"
  },
  {
    "User": "Eike",
    "Artists": [
      "Sick Puppies"
    ],
    "ArtistsString": "Sick Puppies",
    "Track": "Gunfight",
    "TrackId": "0R5tVWACu5evNC8bwHFeY0",
    "Genres": [
      "alternative metal",
      "nu metal",
      "pop punk",
      "post-grunge",
      "rap metal",
      "rap rock"
    ],
    "GenresString": "alternative metal; nu metal; pop punk; post-grunge; rap metal; rap rock"
  },
  {
    "User": "Eike",
    "Artists": [
      "Nothingface"
    ],
    "ArtistsString": "Nothingface",
    "Track": "Ether",
    "TrackId": "7JvrhruAYrdEnJaceVM6WH",
    "Genres": [
      "alternative metal",
      "groove metal",
      "industrial metal",
      "metalcore",
      "nu metal",
      "rap metal",
      "rap rock"
    ],
    "GenresString": "alternative metal; groove metal; industrial metal; metalcore; nu metal; rap metal; rap rock"
  },
  {
    "User": "Eike",
    "Artists": [
      "Agnostic Front"
    ],
    "ArtistsString": "Agnostic Front",
    "Track": "For My Family",
    "TrackId": "4Y4fGklrIKERF6TixxvLQi",
    "Genres": [
      "crossover thrash",
      "groove metal",
      "hardcore",
      "hardcore punk",
      "melodic hardcore",
      "oi",
      "punk",
      "rap metal",
      "rap rock",
      "skate punk",
      "straight edge"
    ],
    "GenresString": "crossover thrash; groove metal; hardcore; hardcore punk; melodic hardcore; oi; punk; rap metal; rap rock; skate punk; straight edge"
  },
  {
    "User": "Eike",
    "Artists": [
      "Lord Of The Lost"
    ],
    "ArtistsString": "Lord Of The Lost",
    "Track": "Die Tomorrow",
    "TrackId": "2wDfDRU5qDtqj2pxKZn1C6",
    "Genres": [
      "gothic metal",
      "heavy gothic rock",
      "medieval rock",
      "neue deutsche harte"
    ],
    "GenresString": "gothic metal; heavy gothic rock; medieval rock; neue deutsche harte"
  },
  {
    "User": "Eike",
    "Artists": [
      "Velcra"
    ],
    "ArtistsString": "Velcra",
    "Track": "My Law",
    "TrackId": "3ia8r68JAcaGez0E0WW8Xb",
    "Genres": [
      "finnish metal",
      "suomi rock"
    ],
    "GenresString": "finnish metal; suomi rock"
  },
  {
    "User": "Eike",
    "Artists": [
      "Orianthi"
    ],
    "ArtistsString": "Orianthi",
    "Track": "Suffocated",
    "TrackId": "5zTHrgDaT02LDyLHd70txv",
    "Genres": [
      "candy pop"
    ],
    "GenresString": "candy pop"
  },
  {
    "User": "Eike",
    "Artists": [
      "Tuoni"
    ],
    "ArtistsString": "Tuoni",
    "Track": "Räsäinen Risti",
    "TrackId": "69khygpluSCrkmS6HItpD6",
    "Genres": [
      "finnish metal"
    ],
    "GenresString": "finnish metal"
  },
  {
    "User": "Eike",
    "Artists": [
      "Abnormality"
    ],
    "ArtistsString": "Abnormality",
    "Track": "Monarch Omega",
    "TrackId": "5RbqNB5HMFkyqXLDdxn0jP",
    "Genres": [
      "brutal death metal",
      "deathgrind",
      "slam death metal",
      "technical brutal death metal",
      "technical death metal"
    ],
    "GenresString": "brutal death metal; deathgrind; slam death metal; technical brutal death metal; technical death metal"
  },
  {
    "User": "Eike",
    "Artists": [
      "Mors Principium Est"
    ],
    "ArtistsString": "Mors Principium Est",
    "Track": "God Has Fallen",
    "TrackId": "1DbX8bRauglTfR7buCMetJ",
    "Genres": [
      "death metal",
      "finnish metal",
      "folk metal",
      "gothic metal",
      "groove metal",
      "melodic death metal",
      "melodic metalcore",
      "metal",
      "metalcore",
      "progressive metal",
      "symphonic black metal",
      "technical death metal",
      "viking metal"
    ],
    "GenresString": "death metal; finnish metal; folk metal; gothic metal; groove metal; melodic death metal; melodic metalcore; metal; metalcore; progressive metal; symphonic black metal; technical death metal; viking metal"
  },
  {
    "User": "Eike",
    "Artists": [
      "Rage"
    ],
    "ArtistsString": "Rage",
    "Track": "Straight To Hell",
    "TrackId": "6SZIcW7ZZvzIWGkcim7D7v",
    "Genres": [
      "german metal",
      "hard rock",
      "metal",
      "neo classical metal",
      "neo-trad metal",
      "nwobhm",
      "power metal",
      "progressive metal",
      "speed metal",
      "thrash metal"
    ],
    "GenresString": "german metal; hard rock; metal; neo classical metal; neo-trad metal; nwobhm; power metal; progressive metal; speed metal; thrash metal"
  },
  {
    "User": "Eike",
    "Artists": [
      "Skitarg"
    ],
    "ArtistsString": "Skitarg",
    "Track": "Utvecklingsstörd",
    "TrackId": "63BSu4HWWwF0DtuI4TYJzB",
    "Genres": [
      "danspunk",
      "swedish alternative rock"
    ],
    "GenresString": "danspunk; swedish alternative rock"
  },
  {
    "User": "Eike",
    "Artists": [
      "Acrania"
    ],
    "ArtistsString": "Acrania",
    "Track": "Disillusion in a Discordant System",
    "TrackId": "2TOQIuYQUzHVK72RgEeXpX",
    "Genres": [
      "death core",
      "progressive deathcore"
    ],
    "GenresString": "death core; progressive deathcore"
  },
  {
    "User": "Eike",
    "Artists": [
      "Adept"
    ],
    "ArtistsString": "Adept",
    "Track": "Black Veins",
    "TrackId": "5tuhbAXcjXeZOHVGYkNHGx",
    "Genres": [
      "melodic death metal",
      "melodic metalcore",
      "metalcore",
      "screamo",
      "swedish alternative rock"
    ],
    "GenresString": "melodic death metal; melodic metalcore; metalcore; screamo; swedish alternative rock"
  },
  {
    "User": "Eike",
    "Artists": [
      "Anew Revolution"
    ],
    "ArtistsString": "Anew Revolution",
    "Track": "Head Against The Wall",
    "TrackId": "3puXu8JBonOBLYzONfMVCH",
    "Genres": [
      "alternative metal",
      "hard alternative",
      "nu metal"
    ],
    "GenresString": "alternative metal; hard alternative; nu metal"
  },
  {
    "User": "Eike",
    "Artists": [
      "Noumena"
    ],
    "ArtistsString": "Noumena",
    "Track": "Misanthropolis",
    "TrackId": "7A1t8mZHVDMwqcw5fPS9Xc",
    "Genres": [
      "finnish metal",
      "folk metal",
      "gothic metal",
      "melodic death metal",
      "viking metal"
    ],
    "GenresString": "finnish metal; folk metal; gothic metal; melodic death metal; viking metal"
  },
  {
    "User": "Eike",
    "Artists": [
      "Charon"
    ],
    "ArtistsString": "Charon",
    "Track": "Colder",
    "TrackId": "2QTT3JLnxDzoS8YRI2Hhht",
    "Genres": [
      "finnish metal",
      "gothic metal",
      "gothic symphonic metal",
      "melodic death metal",
      "symphonic metal"
    ],
    "GenresString": "finnish metal; gothic metal; gothic symphonic metal; melodic death metal; symphonic metal"
  },
  {
    "User": "Eike",
    "Artists": [
      "Crossfaith"
    ],
    "ArtistsString": "Crossfaith",
    "Track": "Jägerbomb",
    "TrackId": "0HJj7WHJAXklI6IkW1Ck2l",
    "Genres": [
      "j-metal",
      "j-rock",
      "metalcore",
      "screamo",
      "visual kei"
    ],
    "GenresString": "j-metal; j-rock; metalcore; screamo; visual kei"
  },
  {
    "User": "Eike",
    "Artists": [
      "Klamydia"
    ],
    "ArtistsString": "Klamydia",
    "Track": "Rakas hullu",
    "TrackId": "1rvK9zOXmOnOVJorQ3pPFA",
    "Genres": [
      "finnish dance pop",
      "finnish hip hop",
      "finnish pop",
      "suomi rock"
    ],
    "GenresString": "finnish dance pop; finnish hip hop; finnish pop; suomi rock"
  },
  {
    "User": "Eike",
    "Artists": [
      "D. Randall Blythe",
      "Westfield Massacre"
    ],
    "ArtistsString": "D. Randall Blythe; Westfield Massacre",
    "Track": "Underneath the Skin (feat. D. Randall Blythe)",
    "TrackId": "336lKDsrEIq7VKpJns9KAA",
    "Genres": [
      "groove metal"
    ],
    "GenresString": "groove metal"
  },
  {
    "User": "Eike",
    "Artists": [
      "Humanity's Last Breath"
    ],
    "ArtistsString": "Humanity's Last Breath",
    "Track": "Shoals",
    "TrackId": "4G9yHMHsObpKAtvK1KaMjT",
    "Genres": [
      "brutal deathcore",
      "death core",
      "djent",
      "progressive deathcore"
    ],
    "GenresString": "brutal deathcore; death core; djent; progressive deathcore"
  },
  {
    "User": "Eike",
    "Artists": [
      "Exotype"
    ],
    "ArtistsString": "Exotype",
    "Track": "Stand Up",
    "TrackId": "3kY2RpA4NNNcT2obIRO2JO",
    "Genres": [
      "death core",
      "post-post-hardcore",
      "post-screamo"
    ],
    "GenresString": "death core; post-post-hardcore; post-screamo"
  },
  {
    "User": "Eike",
    "Artists": [
      "Firespawn"
    ],
    "ArtistsString": "Firespawn",
    "Track": "Lucifer Has Spoken",
    "TrackId": "7eR6wBI1PIFLQe2fvPiEWi",
    "Genres": [
      "death metal",
      "melodic death metal"
    ],
    "GenresString": "death metal; melodic death metal"
  },
  {
    "User": "Eike",
    "Artists": [
      "MyGrain"
    ],
    "ArtistsString": "MyGrain",
    "Track": "Alienation",
    "TrackId": "1bfygUzDbbwGpHkT56Op5Y",
    "Genres": [
      "finnish metal",
      "melodic death metal",
      "melodic metalcore"
    ],
    "GenresString": "finnish metal; melodic death metal; melodic metalcore"
  },
  {
    "User": "Eike",
    "Artists": [
      "Sea Of Treachery"
    ],
    "ArtistsString": "Sea Of Treachery",
    "Track": "Misery Business (Paramore Cover)",
    "TrackId": "3j2nVwTxtOcnt5sEbUntMf",
    "Genres": [
      "death core",
      "melodic metalcore",
      "metalcore"
    ],
    "GenresString": "death core; melodic metalcore; metalcore"
  },
  {
    "User": "Eike",
    "Artists": [
      "Samael"
    ],
    "ArtistsString": "Samael",
    "Track": "Rain",
    "TrackId": "1r9DNUBPD0X1e05BMQkDNz",
    "Genres": [
      "black metal",
      "death metal",
      "doom metal",
      "folk metal",
      "gothic metal",
      "melodic death metal",
      "metal",
      "pagan black metal",
      "symphonic black metal",
      "viking metal"
    ],
    "GenresString": "black metal; death metal; doom metal; folk metal; gothic metal; melodic death metal; metal; pagan black metal; symphonic black metal; viking metal"
  },
  {
    "User": "Eike",
    "Artists": [
      "Swallow The Sun"
    ],
    "ArtistsString": "Swallow The Sun",
    "Track": "Falling World",
    "TrackId": "3yhrnN6aNKQ9Nzzlcd7LSL",
    "Genres": [
      "doom metal",
      "folk metal",
      "gothic metal",
      "melodic death metal",
      "metal",
      "pagan black metal",
      "progressive metal",
      "symphonic black metal",
      "viking metal"
    ],
    "GenresString": "doom metal; folk metal; gothic metal; melodic death metal; metal; pagan black metal; progressive metal; symphonic black metal; viking metal"
  },
  {
    "User": "Eike",
    "Artists": [
      "August Burns Red"
    ],
    "ArtistsString": "August Burns Red",
    "Track": "White Washed",
    "TrackId": "5xcYdoWHur82zA5KYHlgJk",
    "Genres": [
      "christian christmas",
      "christian metal",
      "heavy christmas",
      "melodic metalcore",
      "metalcore",
      "pop christmas",
      "punk christmas",
      "rap metal",
      "screamo"
    ],
    "GenresString": "christian christmas; christian metal; heavy christmas; melodic metalcore; metalcore; pop christmas; punk christmas; rap metal; screamo"
  },
  {
    "User": "Philipp",
    "Artists": [
      "Frank Ocean",
      "Steve Lacy",
      "Tyler, The Creator"
    ],
    "ArtistsString": "Frank Ocean; Steve Lacy; Tyler, The Creator",
    "Track": "911 / Mr. Lonely",
    "TrackId": "4bEcoz1OcfMgUbp2ft8ieQ",
    "Genres": [
      "dance pop",
      "hip hop",
      "indie r&b",
      "neo soul",
      "pop",
      "pop rap",
      "pop rap",
      "rap",
      "rap",
      "southern hip hop",
      "trap music"
    ],
    "GenresString": "dance pop; hip hop; indie r&b; neo soul; pop; pop rap; pop rap; rap; rap; southern hip hop; trap music"
  },
  {
    "User": "Philipp",
    "Artists": [
      "Dizzee Rascal",
      "Donae'o",
      "JME"
    ],
    "ArtistsString": "Dizzee Rascal; Donae'o; JME",
    "Track": "Black",
    "TrackId": "2ZiAw2C68PTUnmhRJECSEA",
    "Genres": [
      "azonto",
      "bassline",
      "deep groove house",
      "grime",
      "grime",
      "grime",
      "house",
      "house",
      "pop rap",
      "rap",
      "tropical house",
      "uk funky",
      "uk garage"
    ],
    "GenresString": "azonto; bassline; deep groove house; grime; grime; grime; house; house; pop rap; rap; tropical house; uk funky; uk garage"
  },
  {
    "User": "Philipp",
    "Artists": [
      "Asher Roth"
    ],
    "ArtistsString": "Asher Roth",
    "Track": "Common Knowledge",
    "TrackId": "0EYIweGN8djdewwF5rRMYV",
    "Genres": [
      "hip hop",
      "pop rap",
      "rap",
      "southern hip hop",
      "underground pop rap"
    ],
    "GenresString": "hip hop; pop rap; rap; southern hip hop; underground pop rap"
  },
  {
    "User": "Philipp",
    "Artists": [
      "Liam Bailey",
      "SHY FX"
    ],
    "ArtistsString": "Liam Bailey; SHY FX",
    "Track": "Soon Come",
    "TrackId": "2FgAvIPnk7PEx8IGSpe3NF",
    "Genres": [
      "drum and bass",
      "electronic",
      "grime",
      "house",
      "jump up",
      "jungle",
      "liquid funk",
      "speed garage",
      "uk garage"
    ],
    "GenresString": "drum and bass; electronic; grime; house; jump up; jungle; liquid funk; speed garage; uk garage"
  },
  {
    "User": "Philipp",
    "Artists": [
      "Dirty Dike"
    ],
    "ArtistsString": "Dirty Dike",
    "Track": "Hi I'm James",
    "TrackId": "2eIVBIo9uHCrrHo3j8XpBr",
    "Genres": [
      "grime",
      "uk hip hop"
    ],
    "GenresString": "grime; uk hip hop"
  },
  {
    "User": "Philipp",
    "Artists": [
      "Bladee",
      "Yung Lean"
    ],
    "ArtistsString": "Bladee; Yung Lean",
    "Track": "Hennessy & Sailor Moon",
    "TrackId": "1Tx9d3LttUbrogmblhfQKY",
    "Genres": [
      "swedish hip hop",
      "underground hip hop",
      "underground hip hop"
    ],
    "GenresString": "swedish hip hop; underground hip hop; underground hip hop"
  },
  {
    "User": "Philipp",
    "Artists": [
      "PROSE"
    ],
    "ArtistsString": "PROSE",
    "Track": "Run With Faith",
    "TrackId": "1SJUmvqVcB9lQSiEiFPtUR",
    "Genres": [
      "indie anthem-folk"
    ],
    "GenresString": "indie anthem-folk"
  },
  {
    "User": "Philipp",
    "Artists": [
      "The WDNG Crshrs"
    ],
    "ArtistsString": "The WDNG Crshrs",
    "Track": "Combination",
    "TrackId": "33gLJdN5yD4U5SgunuQOzT",
    "Genres": [],
    "GenresString": ""
  },
  {
    "User": "Philipp",
    "Artists": [
      "Soul’Art"
    ],
    "ArtistsString": "Soul’Art",
    "Track": "Django",
    "TrackId": "1ELNC7EfFguAGEH1JzUQ1I",
    "Genres": [],
    "GenresString": ""
  },
  {
    "User": "Philipp",
    "Artists": [
      "X-Phaze"
    ],
    "ArtistsString": "X-Phaze",
    "Track": "Just Another Saturday",
    "TrackId": "2Bx5FaWDbRs6FD6kBhOLad",
    "Genres": [],
    "GenresString": ""
  },
  {
    "User": "Philipp",
    "Artists": [
      "Camo & Krooked"
    ],
    "ArtistsString": "Camo & Krooked",
    "Track": "Good Times Bad Times",
    "TrackId": "44nRLXNwTmTIV7Zk7lRol5",
    "Genres": [
      "brostep",
      "chillstep",
      "drum and bass",
      "edm",
      "jump up",
      "liquid funk",
      "neurofunk"
    ],
    "GenresString": "brostep; chillstep; drum and bass; edm; jump up; liquid funk; neurofunk"
  },
  {
    "User": "Philipp",
    "Artists": [
      "Everything Is Recorded",
      "Giggs"
    ],
    "ArtistsString": "Everything Is Recorded; Giggs",
    "Track": "Early This Morning",
    "TrackId": "1rOwEgH4ZjJgw8YVgAcDlj",
    "Genres": [
      "deep groove house",
      "grime",
      "house",
      "uk hip hop"
    ],
    "GenresString": "deep groove house; grime; house; uk hip hop"
  },
  {
    "User": "Philipp",
    "Artists": [
      "Khalid"
    ],
    "ArtistsString": "Khalid",
    "Track": "Saved",
    "TrackId": "248OFOZef6ShXv6DGgbnxU",
    "Genres": [],
    "GenresString": ""
  },
  {
    "User": "Philipp",
    "Artists": [
      "Chet Faker"
    ],
    "ArtistsString": "Chet Faker",
    "Track": "Cigarettes & Loneliness",
    "TrackId": "1JJb3u2uktQHsJu5wMv9qA",
    "Genres": [
      "australian alternative rock",
      "downtempo",
      "indie r&b"
    ],
    "GenresString": "australian alternative rock; downtempo; indie r&b"
  },
  {
    "User": "Philipp",
    "Artists": [
      "Hybrid Minds",
      "Tiffani Juno"
    ],
    "ArtistsString": "Hybrid Minds; Tiffani Juno",
    "Track": "Touch",
    "TrackId": "0Y8GhAQnCRVlq4XyQQKSMm",
    "Genres": [
      "chillstep",
      "drum and bass",
      "liquid funk",
      "neurofunk"
    ],
    "GenresString": "chillstep; drum and bass; liquid funk; neurofunk"
  },
  {
    "User": "Philipp",
    "Artists": [
      "Wandl"
    ],
    "ArtistsString": "Wandl",
    "Track": "Cola",
    "TrackId": "63pEJLtuuf9JvzrxNJw0MO",
    "Genres": [],
    "GenresString": ""
  },
  {
    "User": "Philipp",
    "Artists": [
      "@Peace",
      "P-Money"
    ],
    "ArtistsString": "@Peace; P-Money",
    "Track": "Finding God",
    "TrackId": "5vM72tI94AY8Qm80SzAU6h",
    "Genres": [
      "grime",
      "kiwi rock",
      "polynesian pop"
    ],
    "GenresString": "grime; kiwi rock; polynesian pop"
  },
  {
    "User": "Philipp",
    "Artists": [
      "NxWorries"
    ],
    "ArtistsString": "NxWorries",
    "Track": "Suede",
    "TrackId": "7kFxZ5ckpMi2RhN1WH8cn2",
    "Genres": [
      "alternative hip hop",
      "deep indie r&b",
      "escape room",
      "hip hop",
      "indie r&b",
      "neo soul",
      "underground hip hop"
    ],
    "GenresString": "alternative hip hop; deep indie r&b; escape room; hip hop; indie r&b; neo soul; underground hip hop"
  },
  {
    "User": "Philipp",
    "Artists": [
      "LIONAIRE"
    ],
    "ArtistsString": "LIONAIRE",
    "Track": "Cartoons & Cereals",
    "TrackId": "4sbIMb4uwwp3QquS8uSqt4",
    "Genres": [
      "bass trap",
      "deep german hip hop",
      "deep underground hip hop"
    ],
    "GenresString": "bass trap; deep german hip hop; deep underground hip hop"
  },
  {
    "User": "Philipp",
    "Artists": [
      "Bausa",
      "Marvin Game"
    ],
    "ArtistsString": "Bausa; Marvin Game",
    "Track": "Kleine",
    "TrackId": "1S5iNaikN0l8Gte6hYK8CA",
    "Genres": [
      "deep german hip hop",
      "deep german hip hop",
      "german hip hop",
      "german hip hop"
    ],
    "GenresString": "deep german hip hop; deep german hip hop; german hip hop; german hip hop"
  },
  {
    "User": "Philipp",
    "Artists": [
      "Roots Manuva"
    ],
    "ArtistsString": "Roots Manuva",
    "Track": "Don’t Breathe Out",
    "TrackId": "0BP1UoPOQpxEaR7kjn2mNX",
    "Genres": [
      "big beat",
      "electronic",
      "grime",
      "hip hop",
      "ninja",
      "nu jazz",
      "trip hop",
      "turntablism",
      "uk garage",
      "uk hip hop"
    ],
    "GenresString": "big beat; electronic; grime; hip hop; ninja; nu jazz; trip hop; turntablism; uk garage; uk hip hop"
  },
  {
    "User": "Philipp",
    "Artists": [
      "Rainbow Kitten Surprise"
    ],
    "ArtistsString": "Rainbow Kitten Surprise",
    "Track": "Seven",
    "TrackId": "465hVdgg75kPgRdpJfEFFT",
    "Genres": [
      "indie pop",
      "indie poptimism",
      "indie psych-rock",
      "indietronica",
      "modern rock",
      "stomp and holler"
    ],
    "GenresString": "indie pop; indie poptimism; indie psych-rock; indietronica; modern rock; stomp and holler"
  },
  {
    "User": "Philipp",
    "Artists": [
      "Jam Baxter"
    ],
    "ArtistsString": "Jam Baxter",
    "Track": "Brains",
    "TrackId": "3dqDRmye4pQMEHBFvJxhsA",
    "Genres": [
      "uk hip hop"
    ],
    "GenresString": "uk hip hop"
  },
  {
    "User": "Philipp",
    "Artists": [
      "Little Simz"
    ],
    "ArtistsString": "Little Simz",
    "Track": "Picture Perfect",
    "TrackId": "1O4Q6uCS83UdEgan2QJLvP",
    "Genres": [
      "deep indie r&b",
      "escape room",
      "indie r&b",
      "underground hip hop"
    ],
    "GenresString": "deep indie r&b; escape room; indie r&b; underground hip hop"
  },
  {
    "User": "Philipp",
    "Artists": [
      "Styles Of Beyond"
    ],
    "ArtistsString": "Styles Of Beyond",
    "Track": "Survival Tactics",
    "TrackId": "3jP6KQgQaL2JFEvBW6rELJ",
    "Genres": [],
    "GenresString": ""
  },
  {
    "User": "Philipp",
    "Artists": [
      "The Kooks"
    ],
    "ArtistsString": "The Kooks",
    "Track": "Sweet Emotion",
    "TrackId": "3hyi4CYvZ3K6EqAI2ja7pl",
    "Genres": [
      "garage rock",
      "indie pop",
      "indie rock",
      "modern rock"
    ],
    "GenresString": "garage rock; indie pop; indie rock; modern rock"
  },
  {
    "User": "Philipp",
    "Artists": [
      "Jai Paul"
    ],
    "ArtistsString": "Jai Paul",
    "Track": "BTSTU (Edit)",
    "TrackId": "2NRRrr8ylDK38KD3Ffbw4K",
    "Genres": [
      "indie r&b"
    ],
    "GenresString": "indie r&b"
  },
  {
    "User": "Philipp",
    "Artists": [
      "Greenwood Sharps",
      "Mr Key"
    ],
    "ArtistsString": "Greenwood Sharps; Mr Key",
    "Track": "Icarus Instinct",
    "TrackId": "7un6XcUQVzmMIzrAVXEnbw",
    "Genres": [],
    "GenresString": ""
  },
  {
    "User": "Philipp",
    "Artists": [
      "MGMT",
      "Nipsey Hussle"
    ],
    "ArtistsString": "MGMT; Nipsey Hussle",
    "Track": "Call from the Bank (feat. Mgmt)",
    "TrackId": "4aHN7SjWuXXG9fhpxGaME6",
    "Genres": [
      "alternative dance",
      "alternative rock",
      "brooklyn indie",
      "crunk",
      "dirty south rap",
      "gangster rap",
      "garage rock",
      "hip hop",
      "indie pop",
      "indie rock",
      "indietronica",
      "modern rock",
      "neo-psychedelic",
      "new rave",
      "pop rap",
      "rap",
      "southern hip hop",
      "trap music",
      "west coast trap"
    ],
    "GenresString": "alternative dance; alternative rock; brooklyn indie; crunk; dirty south rap; gangster rap; garage rock; hip hop; indie pop; indie rock; indietronica; modern rock; neo-psychedelic; new rave; pop rap; rap; southern hip hop; trap music; west coast trap"
  },
  {
    "User": "Philipp",
    "Artists": [
      "Akua Naru"
    ],
    "ArtistsString": "Akua Naru",
    "Track": "The World Is Listening",
    "TrackId": "3yoaVe1VOOIDKCuQxv6qwz",
    "Genres": [],
    "GenresString": ""
  },
  {
    "User": "Sabine",
    "Artists": [
      "My Darkest Days"
    ],
    "ArtistsString": "My Darkest Days",
    "Track": "Save Yourself",
    "TrackId": "6FhB5ZyT4JsIJ0ozDlXCIp",
    "Genres": [
      "alternative metal",
      "nu metal",
      "post-grunge",
      "rap metal",
      "rap rock"
    ],
    "GenresString": "alternative metal; nu metal; post-grunge; rap metal; rap rock"
  },
  {
    "User": "Sabine",
    "Artists": [
      "Scooter"
    ],
    "ArtistsString": "Scooter",
    "Track": "Fire",
    "TrackId": "08dJSoLtc8KLm6kVgD2xiH",
    "Genres": [
      "bubblegum dance",
      "eurodance",
      "europop",
      "german techno",
      "happy hardcore"
    ],
    "GenresString": "bubblegum dance; eurodance; europop; german techno; happy hardcore"
  },
  {
    "User": "Sabine",
    "Artists": [
      "Art Of Dying"
    ],
    "ArtistsString": "Art Of Dying",
    "Track": "Get Thru This",
    "TrackId": "6guNV96zDU6sR3i0B5aeAG",
    "Genres": [
      "alternative metal",
      "christian alternative rock",
      "hard alternative",
      "nu metal",
      "post-grunge",
      "post-screamo",
      "rap metal",
      "rap rock"
    ],
    "GenresString": "alternative metal; christian alternative rock; hard alternative; nu metal; post-grunge; post-screamo; rap metal; rap rock"
  },
  {
    "User": "Sabine",
    "Artists": [
      "Black Stone Cherry"
    ],
    "ArtistsString": "Black Stone Cherry",
    "Track": "White Trash Millionaire",
    "TrackId": "3UWYmWg9j8KVV08ANBqcLB",
    "Genres": [
      "alternative metal",
      "nu metal",
      "post-grunge",
      "rap metal",
      "rap rock",
      "rock"
    ],
    "GenresString": "alternative metal; nu metal; post-grunge; rap metal; rap rock; rock"
  },
  {
    "User": "Sabine",
    "Artists": [
      "Eyes Set To Kill"
    ],
    "ArtistsString": "Eyes Set To Kill",
    "Track": "Infected",
    "TrackId": "3xc6vd4aYGPSlxOsp5bkKW",
    "Genres": [
      "melodic metalcore",
      "metalcore",
      "pixie",
      "pop emo",
      "screamo"
    ],
    "GenresString": "melodic metalcore; metalcore; pixie; pop emo; screamo"
  },
  {
    "User": "Sabine",
    "Artists": [
      "Murderdolls"
    ],
    "ArtistsString": "Murderdolls",
    "Track": "Summertime Suicide",
    "TrackId": "2Y8ij4fT5NkqDEaXabT9Gu",
    "Genres": [
      "alternative metal",
      "groove metal",
      "horror punk",
      "industrial metal",
      "nu metal",
      "rap metal"
    ],
    "GenresString": "alternative metal; groove metal; horror punk; industrial metal; nu metal; rap metal"
  },
  {
    "User": "Sabine",
    "Artists": [
      "The Raven Age"
    ],
    "ArtistsString": "The Raven Age",
    "Track": "Angel In Disgrace",
    "TrackId": "4qxXNYWAnjQhLDy0fAg9bL",
    "Genres": [],
    "GenresString": ""
  },
  {
    "User": "Sabine",
    "Artists": [
      "Darkseed"
    ],
    "ArtistsString": "Darkseed",
    "Track": "I Turn to You",
    "TrackId": "0OucQwJBlwv7QzMRQtF3nb",
    "Genres": [
      "gothic metal",
      "gothic symphonic metal",
      "symphonic metal"
    ],
    "GenresString": "gothic metal; gothic symphonic metal; symphonic metal"
  },
  {
    "User": "Sabine",
    "Artists": [
      "Behemoth"
    ],
    "ArtistsString": "Behemoth",
    "Track": "Conquer All",
    "TrackId": "32fGhhfIRJCkiZuDYoQGIU",
    "Genres": [
      "black metal",
      "death metal",
      "deathgrind",
      "groove metal",
      "melodic death metal",
      "melodic metalcore",
      "metal",
      "pagan black metal",
      "symphonic black metal",
      "technical death metal",
      "thrash metal",
      "viking metal"
    ],
    "GenresString": "black metal; death metal; deathgrind; groove metal; melodic death metal; melodic metalcore; metal; pagan black metal; symphonic black metal; technical death metal; thrash metal; viking metal"
  },
  {
    "User": "Sabine",
    "Artists": [
      "Suburban Tribe"
    ],
    "ArtistsString": "Suburban Tribe",
    "Track": "While The World Awaits",
    "TrackId": "4PPNfsPK2Ezcb1w5dtfPEm",
    "Genres": [
      "finnish metal",
      "suomi rock"
    ],
    "GenresString": "finnish metal; suomi rock"
  },
  {
    "User": "Sabine",
    "Artists": [
      "Ember Falls"
    ],
    "ArtistsString": "Ember Falls",
    "Track": "Shut Down With Me",
    "TrackId": "70aKVHWAy7z8B6jpnycVtA",
    "Genres": [],
    "GenresString": ""
  },
  {
    "User": "Sabine",
    "Artists": [
      "Hypnogaja"
    ],
    "ArtistsString": "Hypnogaja",
    "Track": "Scorned",
    "TrackId": "0WHm5g9KcBmnspixmrLuHM",
    "Genres": [
      "hard alternative"
    ],
    "GenresString": "hard alternative"
  },
  {
    "User": "Sabine",
    "Artists": [
      "Anavae"
    ],
    "ArtistsString": "Anavae",
    "Track": "Whatever The Case May be",
    "TrackId": "5HAnye4rdAWCClJyOwWgSD",
    "Genres": [
      "pixie",
      "pop emo"
    ],
    "GenresString": "pixie; pop emo"
  },
  {
    "User": "Sabine",
    "Artists": [
      "Nonpoint"
    ],
    "ArtistsString": "Nonpoint",
    "Track": "Breaking Skin",
    "TrackId": "3uleUeZ5eyYCNGiwcc1Exp",
    "Genres": [
      "alternative metal",
      "groove metal",
      "industrial metal",
      "latin metal",
      "melodic metalcore",
      "metalcore",
      "nu metal",
      "post-grunge",
      "rap metal",
      "rap rock"
    ],
    "GenresString": "alternative metal; groove metal; industrial metal; latin metal; melodic metalcore; metalcore; nu metal; post-grunge; rap metal; rap rock"
  },
  {
    "User": "Sabine",
    "Artists": [
      "Ravenscry"
    ],
    "ArtistsString": "Ravenscry",
    "Track": "The Witness",
    "TrackId": "4Zvz953ld6iZTRogQjwebO",
    "Genres": [
      "gothic metal",
      "gothic symphonic metal",
      "italian metal",
      "symphonic metal"
    ],
    "GenresString": "gothic metal; gothic symphonic metal; italian metal; symphonic metal"
  },
  {
    "User": "Sabine",
    "Artists": [
      "Decyfer Down"
    ],
    "ArtistsString": "Decyfer Down",
    "Track": "Fading",
    "TrackId": "0aAnHzjVQxXyvmbOHGAsfD",
    "Genres": [
      "alternative metal",
      "ccm",
      "christian alternative rock",
      "christian hip hop",
      "christian metal",
      "christian music",
      "christian rock",
      "hard alternative",
      "post-grunge"
    ],
    "GenresString": "alternative metal; ccm; christian alternative rock; christian hip hop; christian metal; christian music; christian rock; hard alternative; post-grunge"
  },
  {
    "User": "Sabine",
    "Artists": [
      "Varien"
    ],
    "ArtistsString": "Varien",
    "Track": "The Scarlet Dawn",
    "TrackId": "4Q5J0IPrX9zxC8vIk1lCVm",
    "Genres": [
      "brostep",
      "catstep",
      "chillstep",
      "complextro",
      "downtempo",
      "edm",
      "electro house",
      "filthstep",
      "tracestep",
      "zapstep"
    ],
    "GenresString": "brostep; catstep; chillstep; complextro; downtempo; edm; electro house; filthstep; tracestep; zapstep"
  },
  {
    "User": "Sabine",
    "Artists": [
      "Bad Religion"
    ],
    "ArtistsString": "Bad Religion",
    "Track": "New Dark Ages",
    "TrackId": "5eNHe2dlIgKGe9SIwu90Va",
    "Genres": [
      "alternative rock",
      "melodic hardcore",
      "pop punk",
      "punk",
      "punk christmas",
      "rock",
      "skate punk"
    ],
    "GenresString": "alternative rock; melodic hardcore; pop punk; punk; punk christmas; rock; skate punk"
  },
  {
    "User": "Sabine",
    "Artists": [
      "Anti-Flag"
    ],
    "ArtistsString": "Anti-Flag",
    "Track": "Broken Bones",
    "TrackId": "6DCQ5i1MY0UiZSCZlcaaMi",
    "Genres": [
      "melodic hardcore",
      "pop punk",
      "punk",
      "ska punk",
      "skate punk"
    ],
    "GenresString": "melodic hardcore; pop punk; punk; ska punk; skate punk"
  },
  {
    "User": "Sabine",
    "Artists": [
      "Raaka-Aine"
    ],
    "ArtistsString": "Raaka-Aine",
    "Track": "Tielle Pimeään",
    "TrackId": "3qh4rZv1sQY5S83JCJCp3R",
    "Genres": [
      "finnish dance pop",
      "finnish pop",
      "suomi rock"
    ],
    "GenresString": "finnish dance pop; finnish pop; suomi rock"
  },
  {
    "User": "Sabine",
    "Artists": [
      "Hell Or Highwater",
      "M. Shadows"
    ],
    "ArtistsString": "Hell Or Highwater; M. Shadows",
    "Track": "Go Alone",
    "TrackId": "3Z1HoJicZr2sVkJ1cpsvZA",
    "Genres": [
      "swedish alternative rock"
    ],
    "GenresString": "swedish alternative rock"
  },
  {
    "User": "Sabine",
    "Artists": [
      "Disarmonia Mundi"
    ],
    "ArtistsString": "Disarmonia Mundi",
    "Track": "Celestial Furnace",
    "TrackId": "2NM3ydi7uBrhux2mYK2lrI",
    "Genres": [
      "groove metal",
      "melodic death metal",
      "melodic metalcore",
      "metalcore"
    ],
    "GenresString": "groove metal; melodic death metal; melodic metalcore; metalcore"
  },
  {
    "User": "Sabine",
    "Artists": [
      "Alice Cooper",
      "Theory of a Deadman"
    ],
    "ArtistsString": "Alice Cooper; Theory of a Deadman",
    "Track": "Savages (feat. Alice Cooper)",
    "TrackId": "0NBlnydSfOcbVlMCbXRIB6",
    "Genres": [
      "album rock",
      "alternative metal",
      "blues-rock",
      "canadian metal",
      "classic rock",
      "glam metal",
      "glam rock",
      "hard rock",
      "heavy christmas",
      "mellow gold",
      "metal",
      "nu metal",
      "pop rock",
      "post-grunge",
      "protopunk",
      "rap metal",
      "rap rock",
      "rock",
      "wrestling"
    ],
    "GenresString": "album rock; alternative metal; blues-rock; canadian metal; classic rock; glam metal; glam rock; hard rock; heavy christmas; mellow gold; metal; nu metal; pop rock; post-grunge; protopunk; rap metal; rap rock; rock; wrestling"
  },
  {
    "User": "Sabine",
    "Artists": [
      "Papercut Massacre"
    ],
    "ArtistsString": "Papercut Massacre",
    "Track": "Lose My Life",
    "TrackId": "6m42f5aMvXXk1qbWIWwUoi",
    "Genres": [
      "hard alternative"
    ],
    "GenresString": "hard alternative"
  },
  {
    "User": "Sabine",
    "Artists": [
      "Girugamesh"
    ],
    "ArtistsString": "Girugamesh",
    "Track": "Break Down",
    "TrackId": "1uEoVo9trcG9ovUfk15kIL",
    "Genres": [
      "j-metal",
      "j-rock",
      "oshare kei",
      "otacore",
      "visual kei"
    ],
    "GenresString": "j-metal; j-rock; oshare kei; otacore; visual kei"
  },
  {
    "User": "Sabine",
    "Artists": [
      "Ill Niño"
    ],
    "ArtistsString": "Ill Niño",
    "Track": "How Can I Live",
    "TrackId": "3H7IV0Aps0rHpqJXQYe5Ma",
    "Genres": [
      "alternative metal",
      "groove metal",
      "industrial metal",
      "industrial rock",
      "latin metal",
      "melodic metalcore",
      "metalcore",
      "nu metal",
      "post-grunge",
      "rap metal",
      "rap rock"
    ],
    "GenresString": "alternative metal; groove metal; industrial metal; industrial rock; latin metal; melodic metalcore; metalcore; nu metal; post-grunge; rap metal; rap rock"
  },
  {
    "User": "Sabine",
    "Artists": [
      "Chimaira"
    ],
    "ArtistsString": "Chimaira",
    "Track": "Resurrection",
    "TrackId": "0uea8qB2AUpgPcKr9yQc2N",
    "Genres": [
      "alternative metal",
      "death core",
      "groove metal",
      "industrial metal",
      "latin metal",
      "melodic death metal",
      "melodic metalcore",
      "metal",
      "metalcore",
      "nu metal",
      "rap metal",
      "rap rock"
    ],
    "GenresString": "alternative metal; death core; groove metal; industrial metal; latin metal; melodic death metal; melodic metalcore; metal; metalcore; nu metal; rap metal; rap rock"
  },
  {
    "User": "Sabine",
    "Artists": [
      "Black Light Discipline"
    ],
    "ArtistsString": "Black Light Discipline",
    "Track": "Walls Inside Us",
    "TrackId": "6rmQF5ViWH7ZpaaZt9G4PQ",
    "Genres": [
      "cyber metal"
    ],
    "GenresString": "cyber metal"
  },
  {
    "User": "Sabine",
    "Artists": [
      "Supercharger"
    ],
    "ArtistsString": "Supercharger",
    "Track": "Blood Red Lips",
    "TrackId": "0Acy3YnqD9sCBZsVXc9DHU",
    "Genres": [
      "punk blues",
      "swedish alternative rock"
    ],
    "GenresString": "punk blues; swedish alternative rock"
  },
  {
    "User": "Sabine",
    "Artists": [
      "Envoi"
    ],
    "ArtistsString": "Envoi",
    "Track": "From a Cage",
    "TrackId": "3YWgircLAgfwHLDwZTAEAV",
    "Genres": [
      "pixie",
      "pop emo",
      "post-screamo"
    ],
    "GenresString": "pixie; pop emo; post-screamo"
  }
]