[
  {
    "User": "Artur",
    "Artists": [
      "Nightcore"
    ],
    "Track": "Witchcraft",
    "TrackId": "",
    "Genres": []
  },
  {
    "User": "Artur",
    "Artists": [
      "OneVoice (Briarcrest Christian High School)"
    ],
    "Track": "Mashup- Radioactive, My Songs Know What You Did In The Dark",
    "TrackId": "",
    "Genres": []
  },
  {
    "User": "Artur",
    "Artists": [
      "Ozzy Stöckel",
      "WoodenToaster"
    ],
    "Track": "Beyond her garden - Dub remix",
    "TrackId": "",
    "Genres": []
  },
  {
    "User": "Kolja",
    "Artists": [
      "Materia"
    ],
    "Track": "Cry Forever",
    "TrackId": "",
    "Genres": []
  },
  {
    "User": "Björn",
    "Artists": [
      "Materia"
    ],
    "Track": "Cry Forever",
    "TrackId": "",
    "Genres": []
  },
  {
    "User": "Philipp",
    "Artists": [
      "Real Prophecy"
    ],
    "Track": "Life Lessons Learned",
    "TrackId": "",
    "Genres": []
  },
  {
    "User": "Artur",
    "Artists": [
      "Written by Wolves"
    ],
    "Track": "Elastic Heart (Rock Version)",
    "TrackId": "4Ng14pKFvjrLPqI1hgYfIN",
    "Genres": [
      "pixie",
      "post-screamo"
    ]
  },
  {
    "User": "Artur",
    "Artists": [
      "Baasik",
      "Black Gryph0n"
    ],
    "Track": "Crusader (Are We There Yet)",
    "TrackId": "3ETkHnOoS67crn1sMlVNVZ",
    "Genres": [
      "antiviral pop",
      "otacore"
    ]
  },
  {
    "User": "Artur",
    "Artists": [
      "We The Kings"
    ],
    "Track": "Any Other Way",
    "TrackId": "2xMLg1z4QjmulQSYMf97RS",
    "Genres": [
      "emo",
      "neo mellow",
      "piano rock",
      "pixie",
      "pop",
      "pop emo",
      "pop punk",
      "pop rock",
      "post-teen pop",
      "teen pop",
      "viral pop"
    ]
  },
  {
    "User": "Artur",
    "Artists": [
      "Area 11"
    ],
    "Track": "Heaven-Piercing Giga Drill",
    "TrackId": "3tEdDUgK9iAcguwp4naFcx",
    "Genres": [
      "antiviral pop",
      "neo-industrial rock",
      "otacore"
    ]
  },
  {
    "User": "Artur",
    "Artists": [
      "Minimusicman"
    ],
    "Track": "Crazy La Paint (Extended Edition)",
    "TrackId": "2S40OIkuYi2EXHKzR49MDJ",
    "Genres": []
  },
  {
    "User": "Artur",
    "Artists": [
      "Bliss n Eso"
    ],
    "Track": "Bomb Like Banksy",
    "TrackId": "731tyRCnJwT866WWcjPeVG",
    "Genres": [
      "australian hip hop",
      "deep australian indie"
    ]
  },
  {
    "User": "Artur",
    "Artists": [
      "Agama"
    ],
    "Track": "Lugia Remix",
    "TrackId": "3xlMQuwg58HK4Wj10wqTI2",
    "Genres": [
      "lithumania"
    ]
  },
  {
    "User": "Artur",
    "Artists": [
      "Niic"
    ],
    "Track": "Paws to the Walls (Album Version)",
    "TrackId": "3F6W10MmpGNvuaVHRgHoqm",
    "Genres": [
      "otacore"
    ]
  },
  {
    "User": "Artur",
    "Artists": [
      "Set It Off"
    ],
    "Track": "I'll Sleep When I'm Dead",
    "TrackId": "5XLVfQhBz6vkJDd9NhgbXQ",
    "Genres": [
      "electropowerpop",
      "emo",
      "otacore",
      "pixie",
      "pop emo",
      "pop punk",
      "punk christmas"
    ]
  },
  {
    "User": "Artur",
    "Artists": [
      "SEGA SOUND TEAM",
      "Tomoya Ohtani"
    ],
    "Track": "Reach For The Stars - Opening Theme - Vocals by Jean Paul Makhlouf of Cash Cash",
    "TrackId": "7apcnerZJaEWx3zJNLhWGt",
    "Genres": []
  },
  {
    "User": "Artur",
    "Artists": [
      "Breakaway"
    ],
    "Track": "Scream",
    "TrackId": "6qTMlTywvKI267Zwgyglc3",
    "Genres": [
      "post-screamo"
    ]
  },
  {
    "User": "Artur",
    "Artists": [
      "Jaki Rose"
    ],
    "Track": "Video Game Song",
    "TrackId": "3d7zzLNzuwnCHQ5FCm8ZZF",
    "Genres": [
      "otacore"
    ]
  },
  {
    "User": "Artur",
    "Artists": [
      "Courtney Jenaé"
    ],
    "Track": "Accelerate (Nightcore Version)",
    "TrackId": "0CuyHaRbnwxK0soqmySXXW",
    "Genres": []
  },
  {
    "User": "Artur",
    "Artists": [
      "I-Exist"
    ],
    "Track": "A Secret Calling",
    "TrackId": "7bSZbBXgr0KoHAE0dvPatd",
    "Genres": [
      "hard alternative",
      "post-screamo"
    ]
  },
  {
    "User": "Artur",
    "Artists": [
      "Anime Kei",
      "Mariatu Conteh"
    ],
    "Track": "The Snow Fairy - From \"Fairy Tale\"",
    "TrackId": "4UBPFD7jAMoLKbqpfXdwhW",
    "Genres": [
      "otacore",
      "scorecore",
      "video game music"
    ]
  },
  {
    "User": "Artur",
    "Artists": [
      "Tokyo Anniversary"
    ],
    "Track": "Bad Apple!! (From Touhou)",
    "TrackId": "0t97vjiM9Lbg5vMqlWZNJT",
    "Genres": [
      "scorecore"
    ]
  },
  {
    "User": "Artur",
    "Artists": [
      "Veracity"
    ],
    "Track": "Nightmare",
    "TrackId": "37u5OydrH2tLihxcFrZivz",
    "Genres": []
  },
  {
    "User": "Artur",
    "Artists": [
      "Manic Bloom"
    ],
    "Track": "Running From The Scene",
    "TrackId": "3ZWfk4Bi9o4fp7iNAjpXV7",
    "Genres": [
      "progressive alternative"
    ]
  },
  {
    "User": "Artur",
    "Artists": [
      "Erica Gibson",
      "Tim White"
    ],
    "Track": "Take Me Over - Radio Edit",
    "TrackId": "0conM1lqspzNQHTcQHqnc6",
    "Genres": []
  },
  {
    "User": "Artur",
    "Artists": [
      "The Animal In Me"
    ],
    "Track": "I Knew You Were Trouble",
    "TrackId": "6bal6He7kynSGdhLtVAHJk",
    "Genres": [
      "pixie",
      "post-screamo"
    ]
  },
  {
    "User": "Artur",
    "Artists": [
      "Brooklyn",
      "Utada"
    ],
    "Track": "Simple and Clean (Ray of Hope Mix)",
    "TrackId": "4vLrBKT6Kkb0Wvm9Sb4oNA",
    "Genres": [
      "anime",
      "japanese r&b",
      "j-dance"
    ]
  },
  {
    "User": "Artur",
    "Artists": [
      "Press Play"
    ],
    "Track": "World Anthem",
    "TrackId": "664h7qJFIOP1QrX9tpeHmf",
    "Genres": [
      "ccm",
      "christian alternative rock",
      "christian christmas",
      "christian hip hop",
      "christian music",
      "christian rock",
      "worship"
    ]
  },
  {
    "User": "Artur",
    "Artists": [
      "R. Master",
      "Shiroku"
    ],
    "Track": "Bad Apple!! (From Touhou) - Vocal Version",
    "TrackId": "6wbMgY83vHNl2YvNN4ScjO",
    "Genres": [
      "otacore",
      "scorecore"
    ]
  },
  {
    "User": "Artur",
    "Artists": [
      "Cardinal"
    ],
    "Track": "Psychosis",
    "TrackId": "71JkKymIMRPrLHDpGEforp",
    "Genres": [
      "post-screamo"
    ]
  },
  {
    "User": "Artur",
    "Artists": [
      "Season to Attack"
    ],
    "Track": "How to Burn One Night",
    "TrackId": "1W38GBgkkhzEtqevrED3CX",
    "Genres": []
  },
  {
    "User": "Artur",
    "Artists": [
      "Eppic",
      "Eppic feat. Poppy",
      "Poppy"
    ],
    "Track": "Hide and Seek",
    "TrackId": "3N3UGIhDUjlcgeupMobmLP",
    "Genres": [
      "viral pop"
    ]
  },
  {
    "User": "Artur",
    "Artists": [
      "Solence"
    ],
    "Track": "Warriors",
    "TrackId": "6gsM7xmG68XjOuXtUjS4Rg",
    "Genres": [
      "post-screamo"
    ]
  },
  {
    "User": "Eike",
    "Artists": [
      "I, Valiance"
    ],
    "Track": "Eye, Visualize",
    "TrackId": "0nhfGvxSXfxUehbeZ1jJGW",
    "Genres": [
      "brutal deathcore",
      "death core"
    ]
  },
  {
    "User": "Eike",
    "Artists": [
      "Visionatica"
    ],
    "Track": "Swamp of the World",
    "TrackId": "5CKD5yU2rSSmytmSPI8C7Y",
    "Genres": [
      "gothic symphonic metal",
      "symphonic metal"
    ]
  },
  {
    "User": "Eike",
    "Artists": [
      "Novelists"
    ],
    "Track": "Echoes",
    "TrackId": "0YgUIG0L4JmeVXftmBxLVi",
    "Genres": [
      "djent"
    ]
  },
  {
    "User": "Eike",
    "Artists": [
      "Entombed A.D."
    ],
    "Track": "Dead Dawn",
    "TrackId": "3HGmJSchoOoNJGwa633dvo",
    "Genres": [
      "death metal"
    ]
  },
  {
    "User": "Eike",
    "Artists": [
      "Obscure of Acacia"
    ],
    "Track": "The Biggest Lie",
    "TrackId": "5vxKOALtTu4CIoPMQoZ6xp",
    "Genres": []
  },
  {
    "User": "Eike",
    "Artists": [
      "Sirona"
    ],
    "Track": "Incur",
    "TrackId": "2yHABL3Vsjq6Jt9oDUUkod",
    "Genres": []
  },
  {
    "User": "Eike",
    "Artists": [
      "Stick To Your Guns"
    ],
    "Track": "Universal Language",
    "TrackId": "2cuxC8oM35ztwtt2D8elgu",
    "Genres": [
      "death core",
      "melodic hardcore",
      "melodic metalcore",
      "metalcore",
      "screamo"
    ]
  },
  {
    "User": "Eike",
    "Artists": [
      "Darke Complex"
    ],
    "Track": "Desperation",
    "TrackId": "0nFJCT044DaFgCVWwHCtQC",
    "Genres": []
  },
  {
    "User": "Eike",
    "Artists": [
      "Chris Cerulli",
      "Shannon Lucas",
      "The Iron Son"
    ],
    "Track": "Unleash Hell (feat. Chris Cerulli & Shannon Lucas)",
    "TrackId": "29jaKkhy1JHNRNkNyrloaS",
    "Genres": []
  },
  {
    "User": "Eike",
    "Artists": [
      "Caulfield"
    ],
    "Track": "Hell Inside My Head",
    "TrackId": "6hfeMSlfaOfYAcziYYRP83",
    "Genres": []
  },
  {
    "User": "Eike",
    "Artists": [
      "Arkona"
    ],
    "Track": "Vozrozhdenie",
    "TrackId": "7qzEEtyUd9fsanV4nSs3Jt",
    "Genres": [
      "folk metal",
      "medieval",
      "medieval rock",
      "power metal",
      "slavic metal",
      "symphonic metal",
      "viking metal"
    ]
  },
  {
    "User": "Eike",
    "Artists": [
      "O'kingdom"
    ],
    "Track": "Serpent",
    "TrackId": "0DRyeHjEyO99ZListinCyr",
    "Genres": []
  },
  {
    "User": "Eike",
    "Artists": [
      "Rivers of Nihil"
    ],
    "Track": "Perpetual Growth Machine",
    "TrackId": "2Hzk6JEgGtpPQ2hqgbaHZs",
    "Genres": [
      "brutal death metal",
      "death core",
      "deathgrind",
      "technical death metal"
    ]
  },
  {
    "User": "Eike",
    "Artists": [
      "Equilibrium Falls"
    ],
    "Track": "System Resistance",
    "TrackId": "3frBPIq96AypXGCMLzOqLr",
    "Genres": []
  },
  {
    "User": "Eike",
    "Artists": [
      "Imperium Dekadenz"
    ],
    "Track": "Dis Manibvs",
    "TrackId": "6sKtFh4BmrnOXpWrv3w45e",
    "Genres": [
      "atmospheric black metal",
      "avantgarde metal",
      "black metal",
      "pagan black metal",
      "symphonic black metal",
      "viking metal",
      "voidgaze"
    ]
  },
  {
    "User": "Eike",
    "Artists": [
      "Dark Funeral"
    ],
    "Track": "Where Shadows Forever Reign",
    "TrackId": "4inmj5F1klS0C1XODSKHW0",
    "Genres": [
      "atmospheric black metal",
      "avantgarde metal",
      "black metal",
      "brutal death metal",
      "dark black metal",
      "death metal",
      "deathgrind",
      "melodic death metal",
      "metal",
      "pagan black metal",
      "swedish metal",
      "symphonic black metal",
      "technical death metal",
      "thrash metal",
      "viking metal"
    ]
  },
  {
    "User": "Eike",
    "Artists": [
      "Girugamesh"
    ],
    "Track": "period",
    "TrackId": "7MeKdSL8O5Dnk6T2mhKbQF",
    "Genres": [
      "anime",
      "j-metal",
      "oshare kei",
      "otacore",
      "visual kei"
    ]
  },
  {
    "User": "Eike",
    "Artists": [
      "Aeons of Corruption"
    ],
    "Track": "Rotten",
    "TrackId": "0ccbzeRr0WP7rdnxmgJjcq",
    "Genres": []
  },
  {
    "User": "Eike",
    "Artists": [
      "Of Mice & Men"
    ],
    "Track": "Real",
    "TrackId": "6bzFJmnLxnhmZQZF3qm7ww",
    "Genres": [
      "alternative metal",
      "emo",
      "metalcore",
      "pixie",
      "pop punk",
      "post-screamo",
      "rap metal",
      "screamo"
    ]
  },
  {
    "User": "Eike",
    "Artists": [
      "Heart Of A Coward"
    ],
    "Track": "Skeletal II - Arise",
    "TrackId": "4CXEm96NMLuuWpSlDTN9R1",
    "Genres": [
      "death core",
      "deep melodic metalcore",
      "djent",
      "melodic metalcore",
      "metalcore"
    ]
  },
  {
    "User": "Eike",
    "Artists": [
      "Diminish The Gods"
    ],
    "Track": "Invasion",
    "TrackId": "6L78GoKQVxPwQWndfdCoCP",
    "Genres": []
  },
  {
    "User": "Eike",
    "Artists": [
      "Candiria"
    ],
    "Track": "The Whole World Will Burn",
    "TrackId": "2wj3mHxZulo6J6yjmgJvyx",
    "Genres": [
      "groove metal",
      "jazz metal",
      "mathcore",
      "metalcore",
      "rap metal",
      "rap rock"
    ]
  },
  {
    "User": "Eike",
    "Artists": [
      "Inquisition"
    ],
    "Track": "From Chaos They Came",
    "TrackId": "2Jt1G2mLBGGVfg1QSCPwqR",
    "Genres": [
      "atmospheric black metal",
      "avantgarde metal",
      "black death",
      "black metal",
      "black thrash",
      "brutal death metal",
      "dark black metal",
      "death metal",
      "deathgrind",
      "doom metal",
      "goregrind",
      "grindcore",
      "heavy christmas",
      "metal",
      "pagan black metal",
      "post-doom metal",
      "post-metal",
      "symphonic black metal",
      "technical death metal",
      "thrash metal",
      "usbm",
      "viking metal",
      "voidgaze"
    ]
  },
  {
    "User": "Eike",
    "Artists": [
      "Denis Stoff",
      "Forever In Combat"
    ],
    "Track": "Lucid Dreams",
    "TrackId": "2GYPwTC9K5IVG6Ud5paxzJ",
    "Genres": [
      "post-post-hardcore",
      "post-screamo"
    ]
  },
  {
    "User": "Eike",
    "Artists": [
      "Pagandom"
    ],
    "Track": "Forever",
    "TrackId": "4S6ZsdomgiuKxOt1SITNo2",
    "Genres": []
  },
  {
    "User": "Eike",
    "Artists": [
      "Omophagia"
    ],
    "Track": "Willing Whore",
    "TrackId": "6oFG0LgV8qVS5mHHrhPGNl",
    "Genres": []
  },
  {
    "User": "Eike",
    "Artists": [
      "As Paradise Falls"
    ],
    "Track": "Equilibrium",
    "TrackId": "0xVMIMKqKL1LQWZqeUsEVO",
    "Genres": []
  },
  {
    "User": "Eike",
    "Artists": [
      "The Dialectic"
    ],
    "Track": "Dominance Displayed",
    "TrackId": "6GARUExQv8PQk4kCrSm1Xb",
    "Genres": [
      "death core"
    ]
  },
  {
    "User": "Eike",
    "Artists": [
      "All Hell"
    ],
    "Track": "Graveyard Dust",
    "TrackId": "6CSXB1cf5ByuwzYSJqo5oc",
    "Genres": []
  },
  {
    "User": "Eike",
    "Artists": [
      "4arm"
    ],
    "Track": "Eyes of the Slain",
    "TrackId": "0YsdX9jO58zydZ7voOWsOx",
    "Genres": [
      "thrash-groove metal"
    ]
  },
  {
    "User": "Kolja",
    "Artists": [
      "Those Who Fear"
    ],
    "Track": "Ten Years",
    "TrackId": "2mY0rczvdDRnPDoqHe5trw",
    "Genres": [
      "christian hardcore",
      "christian metal",
      "deep melodic metalcore"
    ]
  },
  {
    "User": "Kolja",
    "Artists": [
      "Allegaeon"
    ],
    "Track": "Gray Matter Mechanics - Apassionata Ex Machinea",
    "TrackId": "2ZYsMOE4QpWICp8LQR6iku",
    "Genres": [
      "brutal death metal",
      "death core",
      "death metal",
      "deathgrind",
      "djent",
      "groove metal",
      "jazz metal",
      "melodic death metal",
      "melodic metalcore",
      "metalcore",
      "technical death metal"
    ]
  },
  {
    "User": "Kolja",
    "Artists": [
      "Aphyxion"
    ],
    "Track": "Destined To Fail",
    "TrackId": "5MjOPbURVtaw5DuUWLEVxn",
    "Genres": []
  },
  {
    "User": "Kolja",
    "Artists": [
      "Kyng"
    ],
    "Track": "Follow Blindly",
    "TrackId": "3P2SHFvJHchHBH1WG8JnYX",
    "Genres": []
  },
  {
    "User": "Kolja",
    "Artists": [
      "Hanging Garden"
    ],
    "Track": "Penumbra",
    "TrackId": "1w7iyrWQstKTkTrQ4nMcr4",
    "Genres": [
      "doom metal",
      "funeral doom",
      "voidgaze"
    ]
  },
  {
    "User": "Kolja",
    "Artists": [
      "Monte Pittman"
    ],
    "Track": "Pride Comes Before the Fall",
    "TrackId": "4BtcHWR1SVDPCvxbQ0PLZ7",
    "Genres": []
  },
  {
    "User": "Kolja",
    "Artists": [
      "Malevolence"
    ],
    "Track": "In the Face of Death",
    "TrackId": "2F6vNjZZZ8iW6CJx3wv7kL",
    "Genres": [
      "beatdown",
      "deep melodic death metal"
    ]
  },
  {
    "User": "Kolja",
    "Artists": [
      "Equilibrium Falls"
    ],
    "Track": "System Resistance",
    "TrackId": "3frBPIq96AypXGCMLzOqLr",
    "Genres": []
  },
  {
    "User": "Kolja",
    "Artists": [
      "Stick To Your Guns"
    ],
    "Track": "Universal Language",
    "TrackId": "2cuxC8oM35ztwtt2D8elgu",
    "Genres": [
      "death core",
      "melodic hardcore",
      "melodic metalcore",
      "metalcore",
      "screamo"
    ]
  },
  {
    "User": "Kolja",
    "Artists": [
      "Crowbar"
    ],
    "Track": "Falling While Rising",
    "TrackId": "7KH8bAOiAshoNKmLZnqwk7",
    "Genres": [
      "alternative metal",
      "crossover thrash",
      "death metal",
      "doom metal",
      "drone metal",
      "grindcore",
      "groove metal",
      "mathcore",
      "metal",
      "metalcore",
      "nu metal",
      "post-doom metal",
      "post-metal",
      "rap metal",
      "rap rock",
      "sludge metal",
      "speed metal",
      "stoner metal",
      "stoner rock",
      "thrash metal"
    ]
  },
  {
    "User": "Kolja",
    "Artists": [
      "Hundredth"
    ],
    "Track": "Victim",
    "TrackId": "49S4oMwfFTFVSQvQgZu1af",
    "Genres": [
      "alternative emo",
      "anthem emo",
      "metalcore",
      "screamo",
      "screamocore"
    ]
  },
  {
    "User": "Kolja",
    "Artists": [
      "So Hideous"
    ],
    "Track": "To Clasp a Fallen Wish With Broken Fingers",
    "TrackId": "4At3AerXXO2dUmTbQchs7r",
    "Genres": [
      "blackgaze",
      "post-metal",
      "voidgaze"
    ]
  },
  {
    "User": "Kolja",
    "Artists": [
      "DVSR"
    ],
    "Track": "Unconscious",
    "TrackId": "1PKNLziNNRhBdvQtuT0M1n",
    "Genres": [
      "djent",
      "rap metal"
    ]
  },
  {
    "User": "Kolja",
    "Artists": [
      "Blood Red Throne"
    ],
    "Track": "Revocation Of Humankind",
    "TrackId": "1mD1QgkhHK0xvXQl6WeyZR",
    "Genres": [
      "black metal",
      "brutal death metal",
      "death metal",
      "deathgrind",
      "goregrind",
      "grindcore",
      "technical death metal"
    ]
  },
  {
    "User": "Kolja",
    "Artists": [
      "Numenorean"
    ],
    "Track": "Home",
    "TrackId": "7zTOZF5EeB9rf8e1hYfxAy",
    "Genres": [
      "pagan black metal",
      "voidgaze"
    ]
  },
  {
    "User": "Kolja",
    "Artists": [
      "Defiler"
    ],
    "Track": "The Lazarus Sign",
    "TrackId": "7D4glYhuizX4y0Zm6O7MQS",
    "Genres": [
      "death core"
    ]
  },
  {
    "User": "Kolja",
    "Artists": [
      "Violet Cold"
    ],
    "Track": "La Petite Mort",
    "TrackId": "1CDJgRpNpoyU0NiCeklvFO",
    "Genres": [
      "atmospheric black metal",
      "avantgarde metal",
      "pagan black metal",
      "post-doom metal",
      "post-metal",
      "voidgaze"
    ]
  },
  {
    "User": "Kolja",
    "Artists": [
      "Destrage"
    ],
    "Track": "Symphony of the Ego",
    "TrackId": "2FfeQNcfnecDR8fGpfsUaA",
    "Genres": [
      "djent",
      "italian metal",
      "jazz metal",
      "mathcore"
    ]
  },
  {
    "User": "Kolja",
    "Artists": [
      "Ghost Bath"
    ],
    "Track": "Golden Number",
    "TrackId": "2mDtJhHMzKCUDItSkWoCnV",
    "Genres": [
      "atmospheric black metal",
      "avantgarde metal",
      "pagan black metal",
      "post-metal",
      "voidgaze"
    ]
  },
  {
    "User": "Kolja",
    "Artists": [
      "Traitors"
    ],
    "Track": "My Regrets",
    "TrackId": "7ewCUd9zV4aHwQhOmNmB32",
    "Genres": [
      "death core"
    ]
  },
  {
    "User": "Kolja",
    "Artists": [
      "Polar"
    ],
    "Track": "Blood for Blood",
    "TrackId": "4IvZDiCHoitqQ4EefQIrXy",
    "Genres": []
  },
  {
    "User": "Kolja",
    "Artists": [
      "Hatesphere"
    ],
    "Track": "The Executioner",
    "TrackId": "7Homp4sHAJYAmChzokmL5Y",
    "Genres": [
      "death metal",
      "groove metal",
      "melodic death metal",
      "melodic metalcore",
      "metalcore"
    ]
  },
  {
    "User": "Kolja",
    "Artists": [
      "Vader"
    ],
    "Track": "Prayer To The God Of War",
    "TrackId": "2UzslMq5fooqwpGmNie3S1",
    "Genres": [
      "black metal",
      "brutal death metal",
      "death metal",
      "deathgrind",
      "grindcore",
      "groove metal",
      "melodic death metal",
      "melodic metalcore",
      "metal",
      "pagan black metal",
      "speed metal",
      "symphonic black metal",
      "technical death metal",
      "thrash metal",
      "viking metal"
    ]
  },
  {
    "User": "Kolja",
    "Artists": [
      "Waldgeflüster"
    ],
    "Track": "Trümmerfestung",
    "TrackId": "0aNSBZN0P9HGgRX1B5O3LL",
    "Genres": [
      "atmospheric black metal",
      "pagan black metal",
      "voidgaze"
    ]
  },
  {
    "User": "Kolja",
    "Artists": [
      "Homewrecker"
    ],
    "Track": "Prophet Liar",
    "TrackId": "34ohxZDhSQ0ntvYP9xt7fy",
    "Genres": [
      "chaotic hardcore"
    ]
  },
  {
    "User": "Kolja",
    "Artists": [
      "Fit For A King"
    ],
    "Track": "Shadows & Echoes",
    "TrackId": "2vkjzWutGxExP1Ytfk9Lsv",
    "Genres": [
      "christian metal",
      "death core",
      "melodic metalcore",
      "metalcore",
      "post-screamo",
      "rap metal",
      "screamo"
    ]
  },
  {
    "User": "Kolja",
    "Artists": [
      "Arkona"
    ],
    "Track": "Vozrozhdenie",
    "TrackId": "7qzEEtyUd9fsanV4nSs3Jt",
    "Genres": [
      "folk metal",
      "medieval",
      "medieval rock",
      "power metal",
      "slavic metal",
      "symphonic metal",
      "viking metal"
    ]
  },
  {
    "User": "Kolja",
    "Artists": [
      "Withem"
    ],
    "Track": "The Pain I Collected",
    "TrackId": "2sS4tzp1AqEDJv38huBQUw",
    "Genres": []
  },
  {
    "User": "Kolja",
    "Artists": [
      "Wovenwar"
    ],
    "Track": "Censorship",
    "TrackId": "2cUZaOYXnpKOC7ZPnm0pyS",
    "Genres": [
      "christian metal",
      "melodic death metal",
      "melodic metalcore",
      "metal",
      "metalcore",
      "post-screamo"
    ]
  },
  {
    "User": "Björn",
    "Artists": [
      "Arkona"
    ],
    "Track": "Vozrozhdenie",
    "TrackId": "7qzEEtyUd9fsanV4nSs3Jt",
    "Genres": [
      "folk metal",
      "medieval",
      "medieval rock",
      "power metal",
      "slavic metal",
      "symphonic metal",
      "viking metal"
    ]
  },
  {
    "User": "Björn",
    "Artists": [
      "Omnihility"
    ],
    "Track": "Psychotic Annihilation",
    "TrackId": "2ojSWiO94QtiqTsNUTf6CN",
    "Genres": [
      "brutal death metal",
      "technical brutal death metal"
    ]
  },
  {
    "User": "Björn",
    "Artists": [
      "Attila"
    ],
    "Track": "Bulletproof",
    "TrackId": "0BNCOaIahlnWIWz1HP98kg",
    "Genres": [
      "death core",
      "melodic metalcore",
      "metalcore",
      "pixie",
      "post-screamo",
      "rap metal",
      "screamo"
    ]
  },
  {
    "User": "Björn",
    "Artists": [
      "Upon A Burning Body"
    ],
    "Track": "'Til the Break of Dawn",
    "TrackId": "6CwQotoQdahvpnAn65nUZ5",
    "Genres": [
      "death core",
      "groove metal",
      "melodic metalcore",
      "metalcore",
      "nu metal",
      "post-screamo",
      "rap metal",
      "screamo"
    ]
  },
  {
    "User": "Björn",
    "Artists": [
      "Metallica"
    ],
    "Track": "Atlas, Rise!",
    "TrackId": "4lVIjnlyyl3f7qqRtvzbM0",
    "Genres": [
      "alternative metal",
      "hard rock",
      "metal",
      "rock",
      "speed metal",
      "thrash metal"
    ]
  },
  {
    "User": "Björn",
    "Artists": [
      "A Sense of Gravity"
    ],
    "Track": "Echo Chasers",
    "TrackId": "3uYYdAGyoDia1ZLwGX4Syy",
    "Genres": [
      "djent",
      "jazz metal"
    ]
  },
  {
    "User": "Björn",
    "Artists": [
      "Hatesphere"
    ],
    "Track": "The Executioner",
    "TrackId": "7Homp4sHAJYAmChzokmL5Y",
    "Genres": [
      "death metal",
      "groove metal",
      "melodic death metal",
      "melodic metalcore",
      "metalcore"
    ]
  },
  {
    "User": "Björn",
    "Artists": [
      "Charred Walls Of The Damned"
    ],
    "Track": "The Soulless",
    "TrackId": "25R5Aa86vWQfUOcHiqEsSD",
    "Genres": [
      "neo-trad metal",
      "nwothm"
    ]
  },
  {
    "User": "Björn",
    "Artists": [
      "Beacons"
    ],
    "Track": "World in Pain",
    "TrackId": "2gY8V8j3Il28yP3G19Ca7F",
    "Genres": []
  },
  {
    "User": "Björn",
    "Artists": [
      "Helhorse"
    ],
    "Track": "Carry Your Own",
    "TrackId": "6ZjczvG4TvbiQZNaj2KrC4",
    "Genres": [
      "black sludge"
    ]
  },
  {
    "User": "Björn",
    "Artists": [
      "Smoke Signals"
    ],
    "Track": "Moving on",
    "TrackId": "72BwWkWpaAC2QaOlsliid9",
    "Genres": []
  },
  {
    "User": "Björn",
    "Artists": [
      "Omega Virus"
    ],
    "Track": "Golden Calf",
    "TrackId": "0DgyrJAjzm7vA5TVa4UcyD",
    "Genres": [
      "djent"
    ]
  },
  {
    "User": "Björn",
    "Artists": [
      "Aliases"
    ],
    "Track": "Find Where You Hide",
    "TrackId": "0uEAHHZ3a2CAjz7fW0L1KK",
    "Genres": [
      "djent"
    ]
  },
  {
    "User": "Björn",
    "Artists": [
      "Mystic Prophecy"
    ],
    "Track": "Follow the Blind",
    "TrackId": "1RrspbdA86wwAlcmjZHLRh",
    "Genres": [
      "german metal",
      "metal",
      "neo classical metal",
      "neo-trad metal",
      "power metal",
      "progressive metal",
      "speed metal"
    ]
  },
  {
    "User": "Björn",
    "Artists": [
      "The Great Discord"
    ],
    "Track": "The Aging Man (Radio Edit)",
    "TrackId": "7g4UxDAUABurtZNLavSrrY",
    "Genres": []
  },
  {
    "User": "Björn",
    "Artists": [
      "Rob Scallon"
    ],
    "Track": "Envy",
    "TrackId": "2jPG2LuARRiOE70QQvB9Mo",
    "Genres": []
  },
  {
    "User": "Björn",
    "Artists": [
      "Humanity's Last Breath"
    ],
    "Track": "Human Swarm",
    "TrackId": "6QopguYpChUZ4Kp8v4Sm20",
    "Genres": [
      "brutal deathcore",
      "death core",
      "djent"
    ]
  },
  {
    "User": "Björn",
    "Artists": [
      "The Last Ten Seconds of Life"
    ],
    "Track": "Little Black Line",
    "TrackId": "3VjAn3qklwk6GBhndRpvqR",
    "Genres": [
      "brutal deathcore",
      "death core",
      "djent"
    ]
  },
  {
    "User": "Björn",
    "Artists": [
      "Twelve Foot Ninja"
    ],
    "Track": "One Hand Killing",
    "TrackId": "7lt4K9LqL1KgBgxl6Ly3Ud",
    "Genres": [
      "alternative metal",
      "djent",
      "nu metal",
      "progressive alternative",
      "rap metal"
    ]
  },
  {
    "User": "Björn",
    "Artists": [
      "Crobot"
    ],
    "Track": "Not for Sale",
    "TrackId": "46jIxz1aq8UqYWIFvVBgZV",
    "Genres": [
      "stoner rock"
    ]
  },
  {
    "User": "Björn",
    "Artists": [
      "All Hell"
    ],
    "Track": "Graveyard Dust",
    "TrackId": "6CSXB1cf5ByuwzYSJqo5oc",
    "Genres": []
  },
  {
    "User": "Björn",
    "Artists": [
      "Caligula's Horse"
    ],
    "Track": "Marigold",
    "TrackId": "4I5NcGVjREt60IThG2GGu9",
    "Genres": [
      "djent",
      "jazz metal",
      "progressive metal"
    ]
  },
  {
    "User": "Björn",
    "Artists": [
      "Periphery"
    ],
    "Track": "Marigold",
    "TrackId": "2YZZ8qsDdvC008LgtpMoI6",
    "Genres": [
      "alternative metal",
      "djent",
      "melodic metalcore",
      "metalcore",
      "progressive metal"
    ]
  },
  {
    "User": "Björn",
    "Artists": [
      "The Faceless"
    ],
    "Track": "Autotheist Movement I: Create",
    "TrackId": "1YP2n273NgbrjdaLHGOQ4M",
    "Genres": [
      "brutal death metal",
      "death core",
      "death metal",
      "deathgrind",
      "djent",
      "jazz metal",
      "mathcore",
      "melodic metalcore",
      "metalcore",
      "technical death metal"
    ]
  },
  {
    "User": "Björn",
    "Artists": [
      "Carnifex"
    ],
    "Track": "Slow Death",
    "TrackId": "6sSgdKcMrEfL673W5yAiEC",
    "Genres": [
      "death core",
      "deathgrind",
      "groove metal",
      "melodic metalcore",
      "metalcore",
      "technical death metal"
    ]
  },
  {
    "User": "Björn",
    "Artists": [
      "Venom Prison"
    ],
    "Track": "Devoid",
    "TrackId": "03DqaEQugdwTFdalJHU4w6",
    "Genres": [
      "chaotic hardcore"
    ]
  },
  {
    "User": "Björn",
    "Artists": [
      "We Are Wolf"
    ],
    "Track": "Bearer of the Curse",
    "TrackId": "5dy6LgdVo1IHxPD9TGHpdH",
    "Genres": []
  },
  {
    "User": "Björn",
    "Artists": [
      "Parkway Drive"
    ],
    "Track": "Devil's Calling",
    "TrackId": "3ysvcWkYJfyA51ieNhiKA8",
    "Genres": [
      "alternative metal",
      "groove metal",
      "melodic metalcore",
      "metalcore",
      "nu metal",
      "rap metal",
      "screamo"
    ]
  },
  {
    "User": "Björn",
    "Artists": [
      "Primordial"
    ],
    "Track": "Where Greater Men Have Fallen",
    "TrackId": "3cn79MOfraSsCHdeOYm65b",
    "Genres": [
      "atmospheric black metal",
      "avantgarde metal",
      "black metal",
      "celtic rock",
      "doom metal",
      "folk metal",
      "melodic death metal",
      "metal",
      "pagan black metal",
      "symphonic black metal",
      "viking metal",
      "voidgaze"
    ]
  },
  {
    "User": "Andreas",
    "Artists": [
      "P.D.P."
    ],
    "Track": "Die Mother Fucker",
    "TrackId": "1LdYdHyVuSh399v73Q82Y7",
    "Genres": []
  },
  {
    "User": "Andreas",
    "Artists": [
      "Rage"
    ],
    "Track": "Straight To Hell",
    "TrackId": "26Pa5kxwQRqWHhvwSrBf5u",
    "Genres": [
      "german metal",
      "metal",
      "neo classical metal",
      "neo-trad metal",
      "nwobhm",
      "power metal",
      "progressive metal",
      "speed metal",
      "thrash metal"
    ]
  },
  {
    "User": "Andreas",
    "Artists": [
      "Eisregen"
    ],
    "Track": "Elektro Hexe",
    "TrackId": "2EvCDVG6TR9rkhq1agkQ1w",
    "Genres": [
      "german metal",
      "medieval rock",
      "neue deutsche harte"
    ]
  },
  {
    "User": "Andreas",
    "Artists": [
      "Sworn"
    ],
    "Track": "Electro Rock",
    "TrackId": "6hW6O2nwO8wEblVrZJClMm",
    "Genres": [
      "symphonic black metal"
    ]
  },
  {
    "User": "Andreas",
    "Artists": [
      "Heaven's Basement"
    ],
    "Track": "I Am Electric",
    "TrackId": "1wPVBFSy3rs8dcgt5SrmYz",
    "Genres": [
      "deep melodic hard rock",
      "sleaze rock"
    ]
  },
  {
    "User": "Andreas",
    "Artists": [
      "The Exies"
    ],
    "Track": "Hey You",
    "TrackId": "2Pe7SuBE6b8jOtQDH66Gm4",
    "Genres": [
      "alternative metal",
      "hard alternative",
      "nu metal",
      "post-grunge",
      "rap metal"
    ]
  },
  {
    "User": "Andreas",
    "Artists": [
      "Great White"
    ],
    "Track": "Kick Start My Heart",
    "TrackId": "1PN7Ax4uQf1OP5ULW8XANp",
    "Genres": [
      "album rock",
      "classic rock",
      "glam metal",
      "hard rock",
      "heavy christmas",
      "mellow gold",
      "metal",
      "rock"
    ]
  },
  {
    "User": "Andreas",
    "Artists": [
      "(Hed) P.E."
    ],
    "Track": "Renegade",
    "TrackId": "60FFcXqMHC5aFTu62HUrSA",
    "Genres": [
      "alternative metal",
      "funk rock",
      "groove metal",
      "industrial metal",
      "nu metal",
      "post-grunge",
      "rap metal",
      "rap rock"
    ]
  },
  {
    "User": "Andreas",
    "Artists": [
      "Coheed and Cambria"
    ],
    "Track": "Welcome Home",
    "TrackId": "0WZJFaAUl22bUcwsfjoIxV",
    "Genres": [
      "alternative metal",
      "emo",
      "pop punk",
      "post-grunge",
      "screamo"
    ]
  },
  {
    "User": "Andreas",
    "Artists": [
      "Lamb of God"
    ],
    "Track": "Redneck",
    "TrackId": "04EtBLFIxbcVt9NdYgcrpF",
    "Genres": [
      "alternative metal",
      "groove metal",
      "melodic metalcore",
      "metal",
      "metalcore",
      "nu metal",
      "rap metal",
      "rap rock"
    ]
  },
  {
    "User": "Andreas",
    "Artists": [
      "Turisas"
    ],
    "Track": "Rasputin",
    "TrackId": "0W43LnKXzRivi0WPaoBLVO",
    "Genres": [
      "finnish metal",
      "folk metal",
      "melodic death metal",
      "metal",
      "power metal",
      "progressive metal",
      "symphonic metal",
      "viking metal"
    ]
  },
  {
    "User": "Andreas",
    "Artists": [
      "Shinedown"
    ],
    "Track": "Diamond Eyes [Boom-Lay Boom-Lay Boom]",
    "TrackId": "1PLMK1ui86iHHG3FM1N7ue",
    "Genres": [
      "alternative metal",
      "alternative rock",
      "heavy christmas",
      "nu metal",
      "post-grunge",
      "rap metal",
      "rap rock",
      "rock"
    ]
  },
  {
    "User": "Andreas",
    "Artists": [
      "Avenged Sevenfold"
    ],
    "Track": "Paranoid",
    "TrackId": "68A0OXC8UGj4JhmsN4GjBv",
    "Genres": [
      "alternative metal",
      "alternative rock",
      "nu metal",
      "pop punk",
      "post-grunge",
      "rock"
    ]
  },
  {
    "User": "Andreas",
    "Artists": [
      "Cinder"
    ],
    "Track": "Soul Creation",
    "TrackId": "0kl91ZnPeSZZb3Dm4dkZac",
    "Genres": []
  },
  {
    "User": "Andreas",
    "Artists": [
      "Nikki Puppet"
    ],
    "Track": "We Didnt Start The Fire",
    "TrackId": "2o5PpXJ6OGUzpj13Afz6EX",
    "Genres": []
  },
  {
    "User": "Andreas",
    "Artists": [
      "Pain"
    ],
    "Track": "Shut Your Mouth",
    "TrackId": "3kS2bx6TkbG64bUP68KvbP",
    "Genres": [
      "gothic metal",
      "groove metal",
      "industrial metal",
      "melodic death metal",
      "melodic metalcore",
      "metal",
      "neue deutsche harte",
      "nu metal",
      "power metal",
      "progressive metal",
      "swedish alternative rock",
      "symphonic metal"
    ]
  },
  {
    "User": "Andreas",
    "Artists": [
      "Klamydia"
    ],
    "Track": "Pienen pojan elämää",
    "TrackId": "2aeYWVOL3kCqDHp6vq2Mne",
    "Genres": [
      "finnish dance pop",
      "finnish hip hop",
      "finnish pop",
      "suomi rock"
    ]
  },
  {
    "User": "Andreas",
    "Artists": [
      "Wolfmother"
    ],
    "Track": "Joker And The Thief",
    "TrackId": "4juq76lIar8YWOLpYMXUAG",
    "Genres": [
      "alternative rock",
      "blues-rock",
      "classic rock",
      "funk rock",
      "garage rock",
      "indie rock",
      "modern blues",
      "neo-psychedelic",
      "post-grunge",
      "rock"
    ]
  },
  {
    "User": "Andreas",
    "Artists": [
      "Richard Cheese"
    ],
    "Track": "People Equals Shit",
    "TrackId": "795Mm8ChDaLOwmqLUtEbTo",
    "Genres": [
      "comic"
    ]
  },
  {
    "User": "Andreas",
    "Artists": [
      "Bobaflex"
    ],
    "Track": "The Sound of Silence",
    "TrackId": "2enqEvIeAralxE1x61HNix",
    "Genres": [
      "alternative metal",
      "nu metal",
      "rap metal",
      "rap rock"
    ]
  },
  {
    "User": "Andreas",
    "Artists": [
      "Týr"
    ],
    "Track": "The Wild Rover",
    "TrackId": "7F43T4cZCDuBT5NsJah1Wx",
    "Genres": [
      "folk metal",
      "power metal",
      "viking metal"
    ]
  },
  {
    "User": "Andreas",
    "Artists": [
      "Jonathan Coulton"
    ],
    "Track": "Code Monkey",
    "TrackId": "1rIFZk9tTUtHP3vULR5wXe",
    "Genres": [
      "antiviral pop",
      "comic",
      "pop rock",
      "video game music"
    ]
  },
  {
    "User": "Andreas",
    "Artists": [
      "Metalocalypse: Dethklok"
    ],
    "Track": "Bloodlines",
    "TrackId": "31BQPqg0PGatf52fIeu3Hh",
    "Genres": [
      "comic",
      "nu metal"
    ]
  },
  {
    "User": "Andreas",
    "Artists": [
      "Fall Out Boy",
      "John Mayer"
    ],
    "Track": "Beat It - Studio Version",
    "TrackId": "3C65zQ69c8RMiJ3wqB1ogp",
    "Genres": [
      "emo",
      "folk-pop",
      "neo mellow",
      "pop",
      "pop punk",
      "pop rock",
      "singer-songwriter"
    ]
  },
  {
    "User": "Andreas",
    "Artists": [
      "Brick + Mortar"
    ],
    "Track": "Voodoo Child",
    "TrackId": "1J9hEF0MnnHtJk1jA7PCOM",
    "Genres": [
      "indie rockism"
    ]
  },
  {
    "User": "Andreas",
    "Artists": [
      "Skindred"
    ],
    "Track": "Ratrace",
    "TrackId": "6l3XfwxpZJ1ZTKPXoW58RU",
    "Genres": [
      "alternative metal",
      "groove metal",
      "heavy christmas",
      "industrial metal",
      "nu metal",
      "post-grunge",
      "rap metal",
      "rap rock",
      "welsh rock"
    ]
  },
  {
    "User": "Andreas",
    "Artists": [
      "Viejos Contrabandistas"
    ],
    "Track": "Im Shipping Out Boston / The Rights of Man",
    "TrackId": "4fWeMmuz1NIuLWqNmvivAw",
    "Genres": []
  },
  {
    "User": "Andreas",
    "Artists": [
      "KMFDM"
    ],
    "Track": "Ultra",
    "TrackId": "02UsWVUJeCckPaG7oTBD8k",
    "Genres": [
      "digital hardcore",
      "ebm",
      "electro-industrial",
      "electronic",
      "industrial",
      "industrial metal",
      "industrial rock",
      "neue deutsche harte",
      "nu metal"
    ]
  },
  {
    "User": "Andreas",
    "Artists": [
      "The Animals"
    ],
    "Track": "The House Of The Rising Sun",
    "TrackId": "3XC7Jd6SfrQYKZJ6inyRHK",
    "Genres": [
      "album rock",
      "blues-rock",
      "british blues",
      "british invasion",
      "classic rock",
      "folk rock",
      "hard rock",
      "mellow gold",
      "protopunk",
      "psychedelic rock",
      "rock",
      "rock-and-roll",
      "roots rock",
      "singer-songwriter",
      "soft rock"
    ]
  },
  {
    "User": "Andreas",
    "Artists": [
      "South Park"
    ],
    "Track": "San Diego",
    "TrackId": "0p2dFdbKM7QV8r8tdySuoE",
    "Genres": [
      "comic"
    ]
  },
  {
    "User": "Philipp",
    "Artists": [
      "YEAR OF THE OX"
    ],
    "Track": "SEVEN RINGS",
    "TrackId": "5O1GhSlZkt3Wld72OHtXxn",
    "Genres": []
  },
  {
    "User": "Philipp",
    "Artists": [
      "Lonely The Brave"
    ],
    "Track": "Black Mire",
    "TrackId": "6CCLJ76iRqM0ERHv15ntjX",
    "Genres": [
      "alt-indie rock",
      "british alternative rock"
    ]
  },
  {
    "User": "Philipp",
    "Artists": [
      "Berner",
      "Galaxy Atom",
      "Rich Rocka",
      "San Quinn"
    ],
    "Track": "Got That",
    "TrackId": "6uV8s0wWZrRtJV72BHp0H1",
    "Genres": [
      "gangster rap",
      "hyphy",
      "hyphy",
      "hyphy",
      "rap",
      "southern hip hop",
      "trap music",
      "underground hip hop",
      "west coast trap",
      "west coast trap",
      "west coast trap"
    ]
  },
  {
    "User": "Philipp",
    "Artists": [
      "Extreme Music"
    ],
    "Track": "Time Out",
    "TrackId": "1y13JtK17COuvh7G72pksd",
    "Genres": [
      "epicore"
    ]
  },
  {
    "User": "Philipp",
    "Artists": [
      "Trev Rich"
    ],
    "Track": "High Beams",
    "TrackId": "2j7CqMp5Tq4fzxlyJSZzUK",
    "Genres": [
      "deep underground hip hop"
    ]
  },
  {
    "User": "Philipp",
    "Artists": [
      "Chance The Rapper",
      "Joey Purp"
    ],
    "Track": "Girls @ (feat. Chance the Rapper)",
    "TrackId": "00kYtO6UJq0q9aJ1n3iY1c",
    "Genres": [
      "dwn trap",
      "pop rap",
      "rap"
    ]
  },
  {
    "User": "Philipp",
    "Artists": [
      "Wyclef Jean"
    ],
    "Track": "Hendrix",
    "TrackId": "5MZjzyQUEhrfDnnzGsLqnx",
    "Genres": [
      "hip hop",
      "pop christmas",
      "pop rap",
      "rap",
      "soul christmas"
    ]
  },
  {
    "User": "Philipp",
    "Artists": [
      "Jacob Banks",
      "WiDE AWAKE"
    ],
    "Track": "Love Me",
    "TrackId": "6OkP1t5se0cYZTfnNE5gC4",
    "Genres": [
      "bass trap",
      "indie anthem-folk",
      "tracestep"
    ]
  },
  {
    "User": "Philipp",
    "Artists": [
      "Mozes And The Firstborn"
    ],
    "Track": "Marianne",
    "TrackId": "7wvwOzRPKNWJqPa2drXHBk",
    "Genres": []
  },
  {
    "User": "Philipp",
    "Artists": [
      "Desiigner",
      "Tyga"
    ],
    "Track": "Gucci Snakes",
    "TrackId": "3S6Qk3eJctunBqcqC3jmcE",
    "Genres": [
      "dance pop",
      "dwn trap",
      "dwn trap",
      "hip hop",
      "hip hop",
      "pop",
      "pop rap",
      "pop rap",
      "r&b",
      "rap",
      "rap",
      "southern hip hop",
      "southern hip hop",
      "trap music",
      "trap music"
    ]
  },
  {
    "User": "Philipp",
    "Artists": [
      "Charlie Perry",
      "Linguistics",
      "Linguistics feat. Charlie Perry"
    ],
    "Track": "Life's Good",
    "TrackId": "2sWKof7406GQYe2kmhtEMy",
    "Genres": []
  },
  {
    "User": "Philipp",
    "Artists": [
      "Karate Andi",
      "Nico (K.I.Z)"
    ],
    "Track": "Kleid deiner Mutter",
    "TrackId": "3A8TP40r8TyGNgzUEVfGHV",
    "Genres": [
      "deep german hip hop",
      "german hip hop"
    ]
  },
  {
    "User": "Philipp",
    "Artists": [
      "Tiavo"
    ],
    "Track": "Huckleberry Finn",
    "TrackId": "0Xf5WxyYU4QpvbgnN0iVkT",
    "Genres": []
  },
  {
    "User": "Philipp",
    "Artists": [
      "Razz"
    ],
    "Track": "Youth & Enjoyment",
    "TrackId": "4g5QwWZxDTXGDr2mQPnJJ8",
    "Genres": []
  },
  {
    "User": "Philipp",
    "Artists": [
      "James Fate"
    ],
    "Track": "No Breaks",
    "TrackId": "4Mi1N4cEaI8e5w2DXpAznZ",
    "Genres": []
  },
  {
    "User": "Philipp",
    "Artists": [
      "Dame D.O.L.L.A",
      "Paul Rey"
    ],
    "Track": "Bigger Than Us (feat. Paul Rey)",
    "TrackId": "7rwVT5ji3T9oO9oxsW4jbA",
    "Genres": [
      "bass trap",
      "deep underground hip hop"
    ]
  },
  {
    "User": "Philipp",
    "Artists": [
      "VAN HOLZEN"
    ],
    "Track": "Nackt",
    "TrackId": "7eZVVUg0Z7nprAopbtHUUW",
    "Genres": [
      "german indie"
    ]
  },
  {
    "User": "Philipp",
    "Artists": [
      "Chill Bump"
    ],
    "Track": "Seven",
    "TrackId": "2oA1tGcQIBAUrrlmr19BtI",
    "Genres": []
  },
  {
    "User": "Philipp",
    "Artists": [
      "Daye Jack"
    ],
    "Track": "Raw",
    "TrackId": "1KL5oNbR2LJC5Rujsp4LCu",
    "Genres": [
      "escape room",
      "underground hip hop"
    ]
  },
  {
    "User": "Philipp",
    "Artists": [
      "Corner Boy P",
      "Curren$y"
    ],
    "Track": "What a Life",
    "TrackId": "5vwpP1HbU2uGTH4kLLHmKA",
    "Genres": [
      "crunk",
      "deep underground hip hop",
      "dirty south rap",
      "dwn trap",
      "gangster rap",
      "hip hop",
      "indie r&b",
      "pop rap",
      "rap",
      "southern hip hop",
      "underground hip hop",
      "underground hip hop",
      "west coast trap",
      "west coast trap"
    ]
  },
  {
    "User": "Philipp",
    "Artists": [
      "Professor P & DJ Akilles"
    ],
    "Track": "The Interview",
    "TrackId": "3GAc3Nsm7Z5FzDpz7wA2IH",
    "Genres": [
      "swedish hip hop"
    ]
  },
  {
    "User": "Philipp",
    "Artists": [
      "DON BROCO"
    ],
    "Track": "Everybody",
    "TrackId": "2TFWiFlB1t8j2ALmzIRZOa",
    "Genres": [
      "alt-indie rock",
      "british alternative rock",
      "pixie"
    ]
  },
  {
    "User": "Philipp",
    "Artists": [
      "Pretty Vicious"
    ],
    "Track": "Cave Song",
    "TrackId": "1lQLs3mXd7sbu8ebMmp3LU",
    "Genres": [
      "alt-indie rock"
    ]
  },
  {
    "User": "Philipp",
    "Artists": [
      "Hopsin"
    ],
    "Track": "Bout the Business",
    "TrackId": "4lDRCZho3GlmRqOJRjmLfE",
    "Genres": [
      "deep underground hip hop",
      "gangster rap",
      "hip hop",
      "pop rap",
      "rap",
      "trap music",
      "underground hip hop"
    ]
  },
  {
    "User": "Philipp",
    "Artists": [
      "HD",
      "Lil AJ",
      "Shady Nate",
      "Stef Stax"
    ],
    "Track": "Pound Cake Remix (feat. Lil Aj, Stef Stax & Hd)",
    "TrackId": "44B4Mvvrx8MCCLCht8zM0b",
    "Genres": [
      "hyphy",
      "hyphy",
      "hyphy",
      "west coast trap",
      "west coast trap",
      "west coast trap"
    ]
  },
  {
    "User": "Philipp",
    "Artists": [
      "Blueprint",
      "Just Say Plz"
    ],
    "Track": "Long Term",
    "TrackId": "6oFJAGmLuh3Ey7VuBcoVSC",
    "Genres": [
      "abstract hip hop",
      "alternative hip hop",
      "underground rap"
    ]
  },
  {
    "User": "Philipp",
    "Artists": [
      "Deanna",
      "Drunk Girl"
    ],
    "Track": "Don't Stop the Party",
    "TrackId": "22MQaNqXOkTUdg4rawaBCg",
    "Genres": []
  },
  {
    "User": "Philipp",
    "Artists": [
      "Bizarre",
      "Hayze"
    ],
    "Track": "When the Curtain Falls",
    "TrackId": "5IhHDI5AImKOsSfuanKxyV",
    "Genres": [
      "detroit hip hop"
    ]
  },
  {
    "User": "Philipp",
    "Artists": [
      "Cliff Savage"
    ],
    "Track": "Time Shift",
    "TrackId": "0Ik3buLcXW6CsQq40GoNxM",
    "Genres": []
  }
]